{"division": "D92_D2 Messieurs_Ph2 Poule 4", "organisme": "116", "phase": "2", "poule": 10, "cx_poule": 1141193, "classement": [{"clt": "1", "equipe": "NANTERRE ES 3", "pts": "21", "joue": "7", "vic": "7", "nul": "0", "def": "0", "pg": "183", "pp": "107"}, {"clt": "2", "equipe": "PLESSIS ROBINS. 7", "pts": "17", "joue": "7", "vic": "5", "nul": "0", "def": "2", "pg": "164", "pp": "130"}, {"clt": "3", "equipe": "LEVALLOIS SPORT 18", "pts": "15", "joue": "7", "vic": "3", "nul": "2", "def": "2", "pg": "152", "pp": "142"}, {"clt": "4", "equipe": "ISSEENNE E P 10", "pts": "14", "joue": "7", "vic": "2", "nul": "3", "def": "2", "pg": "145", "pp": "149"}, {"clt": "5", "equipe": "BOULOGNE BILLAN 15", "pts": "14", "joue": "7", "vic": "2", "nul": "3", "def": "2", "pg": "141", "pp": "153"}, {"clt": "6", "equipe": "SCEAUX T.T. 5", "pts": "12", "joue": "7", "vic": "2", "nul": "1", "def": "4", "pg": "143", "pp": "137"}, {"clt": "7", "equipe": "MALAKOFF USM 6", "pts": "10", "joue": "7", "vic": "1", "nul": "1", "def": "5", "pg": "128", "pp": "166"}, {"clt": "8", "equipe": "NEUILLY ASPN 10", "pts": "8", "joue": "7", "vic": "1", "nul": "0", "def": "5", "pg": "102", "pp": "174"}], "rencontres": [{"date": "06/02/2026", "equa": "NEUILLY ASPN 10", "equb": "MALAKOFF USM 6", "scorea": "22", "scoreb": "20", "compo_a": [{"nom": "GHATTAS Salah", "pts": 500}, {"nom": "PETRINE Diego", "pts": 528}, {"nom": "L ELEU DE LA SIMONE Edouard", "pts": 644}, {"nom": "NEGRONI Francois Regis", "pts": 512}], "compo_b": [{"nom": "LEONARD Cédric", "pts": 500}, {"nom": "AURIOL Patrice", "pts": 500}, {"nom": "JAKUBOWICZ Jeremie", "pts": 582}, {"nom": "CLEMENT Marceau", "pts": 502}]}, {"date": "06/02/2026", "equa": "PLESSIS ROBINS. 7", "equb": "NANTERRE ES 3", "scorea": "18", "scoreb": "24", "compo_a": [{"nom": "FICHELLE Francois", "pts": 870}, {"nom": "FRELON Eric", "pts": 751}, {"nom": "BERNOT Laurent", "pts": 723}, {"nom": "FRANCOISE Philippe", "pts": 741}], "compo_b": [{"nom": "CADO Christophe", "pts": 858}, {"nom": "ZHOU Adrien", "pts": 651}, {"nom": "SALAUN Pierre", "pts": 878}, {"nom": "MAURATILLE Vincent", "pts": 820}]}, {"date": "06/02/2026", "equa": "SCEAUX T.T. 5", "equb": "BOULOGNE BILLAN 15", "scorea": "21", "scoreb": "21", "compo_a": [{"nom": "NING Jiale", "pts": 528}, {"nom": "LIN Christophe", "pts": 771}, {"nom": "ARDELLIER Michel", "pts": 500}, {"nom": "LE CAM Philippe", "pts": 645}], "compo_b": [{"nom": "MA Qi", "pts": 633}, {"nom": "ADMI Johara", "pts": 636}, {"nom": "PIERRON Guillaume", "pts": 552}, {"nom": "FROMONT Joel", "pts": 628}]}, {"date": "06/02/2026", "equa": "ISSEENNE E P 10", "equb": "LEVALLOIS SPORT 18", "scorea": "21", "scoreb": "21", "compo_a": [{"nom": "DELANDEMARE Stephane", "pts": 500}, {"nom": "LORRE Guillaume", "pts": 625}, {"nom": "LEROUX Gael", "pts": 687}, {"nom": "LENOIR Solen", "pts": 661}], "compo_b": [{"nom": "RENE-CORAIL Raphael", "pts": 655}, {"nom": "HUANG Celia", "pts": 679}, {"nom": "STAMULESCU Alicia", "pts": 582}, {"nom": "LAVIROTTE Jean-Marie", "pts": 500}]}, {"date": "13/02/2026", "equa": "NANTERRE ES 3", "equb": "NEUILLY ASPN 10", "scorea": "28", "scoreb": "10", "compo_a": [{"nom": "PETER Paul", "pts": 934}, {"nom": "RAMIREZ Alexandre", "pts": 791}, {"nom": "SALAUN Pierre", "pts": 878}, {"nom": "CADO Christophe", "pts": 858}], "compo_b": [{"nom": "NEGRONI Francois Regis", "pts": 512}, {"nom": "FURET Olivier", "pts": 500}, {"nom": "MAZELLIER Victoria", "pts": 500}]}, {"date": "13/02/2026", "equa": "BOULOGNE BILLAN 15", "equb": "PLESSIS ROBINS. 7", "scorea": "16", "scoreb": "26", "compo_a": [{"nom": "ADMI Johara", "pts": 636}, {"nom": "MA Qi", "pts": 633}, {"nom": "PIERRON Guillaume", "pts": 552}, {"nom": "KOL Nicolas", "pts": 615}], "compo_b": [{"nom": "GALICH Cyril", "pts": 687}, {"nom": "FICHELLE Francois", "pts": 870}, {"nom": "FRANCOISE Philippe", "pts": 741}, {"nom": "BERNOT Laurent", "pts": 723}]}, {"date": "13/02/2026", "equa": "LEVALLOIS SPORT 18", "equb": "SCEAUX T.T. 5", "scorea": "23", "scoreb": "19", "compo_a": [{"nom": "STAMULESCU Alexandre", "pts": 629}, {"nom": "STAMULESCU Alicia", "pts": 582}, {"nom": "SALAUN Helene", "pts": 529}, {"nom": "LAVIROTTE Jean-Marie", "pts": 500}], "compo_b": [{"nom": "NING Jiale", "pts": 528}, {"nom": "LE CAM Philippe", "pts": 645}, {"nom": "ARDELLIER Michel", "pts": 500}, {"nom": "JOURDAIN Stéphane", "pts": 500}]}, {"date": "13/02/2026", "equa": "MALAKOFF USM 6", "equb": "ISSEENNE E P 10", "scorea": "21", "scoreb": "21", "compo_a": [{"nom": "TIERCELIN Gatien", "pts": 556}, {"nom": "LORRE Guillaume", "pts": 625}, {"nom": "DI FIORE Christophe", "pts": 507}, {"nom": "ANDRE Emmanuel", "pts": 500}], "compo_b": [{"nom": "CLEMENT Marceau", "pts": 502}, {"nom": "LOISEAU Chris", "pts": 500}, {"nom": "CHEN Emily", "pts": 533}, {"nom": "LEFEVRE Maxime", "pts": 500}]}, {"date": "20/03/2026", "equa": "NEUILLY ASPN 10", "equb": "BOULOGNE BILLAN 15", "scorea": "19", "scoreb": "23", "compo_a": [{"nom": "NEGRONI Francois Regis", "pts": 512}, {"nom": "DUFAURE DE LAJARTE Hugo", "pts": 534}, {"nom": "CASTIEL Eleonore", "pts": 500}, {"nom": "GHATTAS Salah", "pts": 500}], "compo_b": [{"nom": "ADMI Johara", "pts": 636}, {"nom": "MA Qi", "pts": 633}, {"nom": "LAINE Guillaume", "pts": 634}, {"nom": "SEGUY Vincent", "pts": 549}]}, {"date": "20/03/2026", "equa": "PLESSIS ROBINS. 7", "equb": "LEVALLOIS SPORT 18", "scorea": "18", "scoreb": "24", "compo_a": [{"nom": "GALICH Cyril", "pts": 687}, {"nom": "FICHELLE Francois", "pts": 870}, {"nom": "FRELON Eric", "pts": 751}, {"nom": "BERNOT Laurent", "pts": 723}], "compo_b": [{"nom": "RENE-CORAIL Raphael", "pts": 655}, {"nom": "KLOETI Sebastien", "pts": 733}, {"nom": "HUANG Celia", "pts": 679}, {"nom": "STAMULESCU Alexandre", "pts": 629}]}, {"date": "20/03/2026", "equa": "SCEAUX T.T. 5", "equb": "ISSEENNE E P 10", "scorea": "19", "scoreb": "23", "compo_a": [{"nom": "RIANT Thierry", "pts": 500}, {"nom": "LIN Christophe", "pts": 771}, {"nom": "JOURDAIN Stéphane", "pts": 500}, {"nom": "CHATEAU Jerome", "pts": 500}], "compo_b": [{"nom": "BAILLY Yann", "pts": 608}, {"nom": "MOCO Mathis", "pts": 552}, {"nom": "DELANDEMARE Stephane", "pts": 500}, {"nom": "TIERCELIN Gatien", "pts": 556}]}, {"date": "20/03/2026", "equa": "MALAKOFF USM 6", "equb": "NANTERRE ES 3", "scorea": "15", "scoreb": "27", "compo_a": [{"nom": "LOISEAU Chris", "pts": 500}, {"nom": "AURIOL Patrice", "pts": 500}, {"nom": "LAUTIE-LAUDAT Arthur", "pts": 500}, {"nom": "CLEMENT Marceau", "pts": 502}], "compo_b": [{"nom": "PETER Paul", "pts": 934}, {"nom": "CLAIRET Christelle", "pts": 607}, {"nom": "CADO Christophe", "pts": 858}, {"nom": "RAMIREZ Alexandre", "pts": 791}]}, {"date": "10/04/2026", "equa": "LEVALLOIS SPORT 18", "equb": "NEUILLY ASPN 10", "scorea": "25", "scoreb": "17", "compo_a": [{"nom": "BAKIR Nolan", "pts": 500}, {"nom": "FURET Olivier", "pts": 500}, {"nom": "NEGRONI Francois Regis", "pts": 512}, {"nom": "MAZELLIER Victoria", "pts": 500}], "compo_b": [{"nom": "RENE-CORAIL Raphael", "pts": 655}, {"nom": "JOURDIER Anais", "pts": 500}, {"nom": "SALAUN Helene", "pts": 529}, {"nom": "LAVIROTTE Jean-Marie", "pts": 500}]}, {"date": "10/04/2026", "equa": "ISSEENNE E P 10", "equb": "PLESSIS ROBINS. 7", "scorea": "19", "scoreb": "23", "compo_a": [{"nom": "FICHELLE Francois", "pts": 870}, {"nom": "FRELON Eric", "pts": 751}, {"nom": "FRANCOISE Philippe", "pts": 741}, {"nom": "BERNOT Laurent", "pts": 723}], "compo_b": [{"nom": "LORRE Guillaume", "pts": 625}, {"nom": "COILLAND Délia", "pts": 598}, {"nom": "MONNAYE Lucas", "pts": 565}, {"nom": "LEROUX Gael", "pts": 687}]}, {"date": "10/04/2026", "equa": "SCEAUX T.T. 5", "equb": "MALAKOFF USM 6", "scorea": "25", "scoreb": "17", "compo_a": [{"nom": "ARDELLIER Michel", "pts": 500}, {"nom": "LIN Christophe", "pts": 771}, {"nom": "JOURDAIN Stéphane", "pts": 500}, {"nom": "LATTES Oscar", "pts": 594}], "compo_b": [{"nom": "LOISEAU Stephen", "pts": 500}, {"nom": "LOISEAU Chris", "pts": 500}, {"nom": "CLEMENT Marceau", "pts": 502}, {"nom": "LEFEVRE Maxime", "pts": 500}]}, {"date": "10/04/2026", "equa": "BOULOGNE BILLAN 15", "equb": "NANTERRE ES 3", "scorea": "14", "scoreb": "28", "compo_a": [{"nom": "SALAUN Pierre", "pts": 878}, {"nom": "RAMIREZ Alexandre", "pts": 791}, {"nom": "CADO Christophe", "pts": 858}, {"nom": "MAURATILLE Vincent", "pts": 820}], "compo_b": [{"nom": "PIERRON Guillaume", "pts": 552}, {"nom": "SEGUY Vincent", "pts": 549}, {"nom": "MA Qi", "pts": 633}, {"nom": "ADMI Johara", "pts": 636}]}, {"date": "07/05/2026", "equa": "NEUILLY ASPN 10", "equb": "ISSEENNE E P 10", "scorea": "19", "scoreb": "23", "compo_a": [{"nom": "FURET Olivier", "pts": 500}, {"nom": "GHATTAS Salah", "pts": 500}, {"nom": "MAZELLIER Victoria", "pts": 500}, {"nom": "CASTIEL Eleonore", "pts": 500}], "compo_b": [{"nom": "RIBAULT Lucien", "pts": 537}, {"nom": "LEROUX Gael", "pts": 687}, {"nom": "DELANDEMARE Stephane", "pts": 500}, {"nom": "ANDRE Emmanuel", "pts": 500}]}, {"date": "08/05/2026", "equa": "PLESSIS ROBINS. 7", "equb": "SCEAUX T.T. 5", "scorea": "25", "scoreb": "17", "compo_a": [{"nom": "GALICH Cyril", "pts": 687}, {"nom": "FICHELLE Francois", "pts": 870}, {"nom": "FRELON Eric", "pts": 751}, {"nom": "FRANCOISE Philippe", "pts": 741}], "compo_b": [{"nom": "CHAMPSAUR Lauris", "pts": 531}, {"nom": "BEULAGUET Stephane", "pts": 505}, {"nom": "LE CAM Philippe", "pts": 645}, {"nom": "LIN Christophe", "pts": 771}]}, {"date": "08/05/2026", "equa": "NANTERRE ES 3", "equb": "LEVALLOIS SPORT 18", "scorea": "23", "scoreb": "19", "compo_a": [{"nom": "RENE-CORAIL Raphael", "pts": 655}, {"nom": "HUANG Celia", "pts": 679}, {"nom": "STAMULESCU Alexandre", "pts": 629}, {"nom": "LAVIROTTE Jean-Marie", "pts": 500}], "compo_b": [{"nom": "CADO Christophe", "pts": 858}, {"nom": "CLAIRET Christelle", "pts": 607}, {"nom": "SALAUN Pierre", "pts": 878}, {"nom": "MAURATILLE Vincent", "pts": 820}]}, {"date": "08/05/2026", "equa": "MALAKOFF USM 6", "equb": "BOULOGNE BILLAN 15", "scorea": "17", "scoreb": "25", "compo_a": [{"nom": "CLEMENT Marceau", "pts": 502}, {"nom": "CHEN Emily", "pts": 533}, {"nom": "LEFEVRE Maxime", "pts": 500}, {"nom": "LAUTIE-LAUDAT Arthur", "pts": 500}], "compo_b": [{"nom": "ADMI Johara", "pts": 636}, {"nom": "DE BONNECHOSE Isabelle", "pts": 634}, {"nom": "D'AVOUT Oscar", "pts": 538}, {"nom": "HESS Lucas", "pts": 567}]}, {"date": "29/05/2026", "equa": "SCEAUX T.T. 5", "equb": "NEUILLY ASPN 10", "scorea": "28", "scoreb": "0", "compo_a": [{"nom": "NING Jiale", "pts": 528}, {"nom": "LE CAM Philippe", "pts": 645}, {"nom": "ARDELLIER Michel", "pts": 500}, {"nom": "LIN Christophe", "pts": 771}], "compo_b": []}, {"date": "29/05/2026", "equa": "PLESSIS ROBINS. 7", "equb": "MALAKOFF USM 6", "scorea": "27", "scoreb": "15", "compo_a": [{"nom": "GALICH Cyril", "pts": 687}, {"nom": "FRANCOISE Philippe", "pts": 741}, {"nom": "BERNOT Laurent", "pts": 723}, {"nom": "FRELON Eric", "pts": 751}], "compo_b": [{"nom": "AURIOL Patrice", "pts": 500}, {"nom": "LOISEAU Stephen", "pts": 500}, {"nom": "LOISEAU Chris", "pts": 500}, {"nom": "JAKUBOWICZ Jeremie", "pts": 582}]}, {"date": "29/05/2026", "equa": "ISSEENNE E P 10", "equb": "NANTERRE ES 3", "scorea": "17", "scoreb": "25", "compo_a": [{"nom": "SALAUN Pierre", "pts": 878}, {"nom": "RAMIREZ Alexandre", "pts": 791}, {"nom": "CADO Christophe", "pts": 858}, {"nom": "MAURATILLE Vincent", "pts": 820}], "compo_b": [{"nom": "LORRE Guillaume", "pts": 625}, {"nom": "DELANDEMARE Stephane", "pts": 500}, {"nom": "TIERCELIN Gatien", "pts": 556}, {"nom": "ANDRE Emmanuel", "pts": 500}]}, {"date": "29/05/2026", "equa": "LEVALLOIS SPORT 18", "equb": "BOULOGNE BILLAN 15", "scorea": "21", "scoreb": "21", "compo_a": [{"nom": "HUANG Celia", "pts": 679}, {"nom": "STAMULESCU Alicia", "pts": 582}, {"nom": "STAMULESCU Alexandre", "pts": 629}, {"nom": "LAVIROTTE Jean-Marie", "pts": 500}], "compo_b": [{"nom": "LAINE Guillaume", "pts": 634}, {"nom": "MA Qi", "pts": 633}, {"nom": "YANG Fan", "pts": 555}, {"nom": "SEGUY Vincent", "pts": 549}]}, {"date": "05/06/2026", "equa": "NEUILLY ASPN 10", "equb": "PLESSIS ROBINS. 7", "scorea": "15", "scoreb": "27", "compo_a": [{"nom": "FURET Olivier", "pts": 500}, {"nom": "NEGRONI Francois Regis", "pts": 512}, {"nom": "MAZELLIER Victoria", "pts": 500}, {"nom": "GHATTAS Salah", "pts": 500}], "compo_b": [{"nom": "GALICH Cyril", "pts": 687}, {"nom": "FRELON Eric", "pts": 751}, {"nom": "FRANCOISE Philippe", "pts": 741}, {"nom": "TANZI William", "pts": 569}]}, {"date": "05/06/2026", "equa": "NANTERRE ES 3", "equb": "SCEAUX T.T. 5", "scorea": "28", "scoreb": "14", "compo_a": [{"nom": "CHATEAU Jerome", "pts": 500}, {"nom": "LE CAM Philippe", "pts": 645}, {"nom": "JOURDAIN Stéphane", "pts": 500}, {"nom": "LIN Christophe", "pts": 771}], "compo_b": [{"nom": "CADO Christophe", "pts": 858}, {"nom": "LELIEPVRE Tom", "pts": 576}, {"nom": "SALAUN Pierre", "pts": 878}, {"nom": "RAMIREZ Alexandre", "pts": 791}]}, {"date": "05/06/2026", "equa": "BOULOGNE BILLAN 15", "equb": "ISSEENNE E P 10", "scorea": "21", "scoreb": "21", "compo_a": [{"nom": "ADMI Johara", "pts": 636}, {"nom": "MA Qi", "pts": 633}, {"nom": "SEGUY Vincent", "pts": 549}, {"nom": "PIERRON Guillaume", "pts": 552}], "compo_b": [{"nom": "LORRE Guillaume", "pts": 625}, {"nom": "LEROUX Gael", "pts": 687}, {"nom": "ANDRE Emmanuel", "pts": 500}, {"nom": "PHILIPP Nicolas", "pts": 500}]}, {"date": "05/06/2026", "equa": "MALAKOFF USM 6", "equb": "LEVALLOIS SPORT 18", "scorea": "23", "scoreb": "19", "compo_a": [{"nom": "HUANG Celia", "pts": 679}, {"nom": "STAMULESCU Alicia", "pts": 582}, {"nom": "SALAUN Helene", "pts": 529}, {"nom": "LAVIROTTE Jean-Marie", "pts": 500}], "compo_b": [{"nom": "CLEMENT Marceau", "pts": 502}, {"nom": "LEGER Renaud Alexandre", "pts": 616}, {"nom": "JAKUBOWICZ Jeremie", "pts": 582}, {"nom": "LEFEVRE Maxime", "pts": 500}]}]}