{"lic": "6221074", "nom": "PIQUET", "prenom": "Sebastien", "club": "08920049", "classement": {"officiel": 737, "mensuel": 755, "debut": 720, "avenir": null}, "timeline": [{"m": "Sept", "v": 720.0}, {"m": "Oct", "v": 720.0}, {"m": "Nov", "v": 751.0}, {"m": "Déc", "v": 751.0}, {"m": "Janv", "v": 742.0}, {"m": "Fév", "v": 756.2}, {"m": "Mars", "v": 753.2}, {"m": "Avr", "v": 765.2}, {"m": "Mai", "v": 760.2}, {"m": "Juin", "v": 789.1}, {"m": "Actuel", "v": 755, "off": true}], "saison": {"V": 50, "D": 42, "parties": 92, "winpct": 54, "perfs": 8, "contre_perfs": 11, "best": {"delta": 185, "opp": "LESEIGNEUR Marvin", "opp_cls": 945, "my": 760, "date": "01/05/2026", "comp": "Tournois"}, "worst": {"delta": 185, "opp": "TSARAFIDY Alain", "opp_cls": 580, "my": 765, "date": "17/04/2026", "comp": "Championnat de Paris"}}, "competitions": [{"key": "tournoi", "label": "Tournois", "V": 15, "D": 21, "pg": 56.6, "pl": -41.2, "perf": 4, "cperf": 2, "best": {"delta": 185, "opp": "LESEIGNEUR Marvin", "opp_cls": 945, "my": 760, "date": "01/05/2026", "comp": "Tournois"}, "worst": {"delta": 15, "opp": "LIN Lucas", "opp_cls": 750, "my": 765, "date": "26/04/2026", "comp": "Tournois"}, "matches": [{"date": "24/05/2026", "opp": "BABLON Timothée", "opp_cls": 784, "won": false, "pts": -3.75}, {"date": "24/05/2026", "opp": "FLORENTIN Clément", "opp_cls": 1202, "won": false, "pts": 0.0}, {"date": "24/05/2026", "opp": "BABLON Timothée", "opp_cls": 784, "won": false, "pts": -3.75}, {"date": "24/05/2026", "opp": "DUMESNY Axel", "opp_cls": 835, "won": true, "pts": 6.0}, {"date": "24/05/2026", "opp": "LIN Kingston", "opp_cls": 671, "won": true, "pts": 3.75}, {"date": "24/05/2026", "opp": "RIOULT Gabriel", "opp_cls": 652, "won": true, "pts": 3.0}, {"date": "24/05/2026", "opp": "LEMAIRE ELLIS Lewis", "opp_cls": 553, "won": true, "pts": 1.5}, {"date": "23/05/2026", "opp": "ROHR Maxence", "opp_cls": 936, "won": false, "pts": -1.5}, {"date": "23/05/2026", "opp": "FEYEL Matthieu", "opp_cls": 585, "won": true, "pts": 2.25}, {"date": "23/05/2026", "opp": "RANGER Baptiste", "opp_cls": 910, "won": false, "pts": -1.5}, {"date": "23/05/2026", "opp": "GNIZAKO Stephane", "opp_cls": 1015, "won": false, "pts": -0.75}, {"date": "23/05/2026", "opp": "MORIN François", "opp_cls": 1181, "won": false, "pts": 0.0}, {"date": "03/05/2026", "opp": "LAO Benjamin", "opp_cls": 773, "won": false, "pts": -3.75}, {"date": "03/05/2026", "opp": "TABURET Adrien", "opp_cls": 852, "won": false, "pts": -3.0}, {"date": "03/05/2026", "opp": "DEJOIE Gerard", "opp_cls": 608, "won": true, "pts": 2.25}, {"date": "03/05/2026", "opp": "IP Maxime", "opp_cls": 554, "won": true, "pts": 1.5}, {"date": "03/05/2026", "opp": "DIAS Lucas", "opp_cls": 751, "won": false, "pts": -3.75}, {"date": "01/05/2026", "opp": "CHABOCHE-SEPTIER Owen", "opp_cls": 992, "won": false, "pts": -0.75}, {"date": "01/05/2026", "opp": "BOUCHARD Edouard", "opp_cls": 1220, "won": false, "pts": 0.0}, {"date": "01/05/2026", "opp": "LENA Sandro", "opp_cls": 772, "won": false, "pts": -3.75}, {"date": "01/05/2026", "opp": "LESEIGNEUR Marvin", "opp_cls": 945, "won": true, "pts": 9.75}, {"date": "01/05/2026", "opp": "CHABRAISON Guenael", "opp_cls": 896, "won": true, "pts": 7.5}, {"date": "01/05/2026", "opp": "BECHET Sasha", "opp_cls": 732, "won": true, "pts": 4.12}, {"date": "01/05/2026", "opp": "JOULAIN Valentin", "opp_cls": 747, "won": true, "pts": 4.5}, {"date": "01/05/2026", "opp": "TOUPENCE Mathieu", "opp_cls": 527, "won": true, "pts": 1.5}, {"date": "26/04/2026", "opp": "BIGOT Armand", "opp_cls": 493, "won": true, "pts": 1.5}, {"date": "26/04/2026", "opp": "TRAORE Ian-Elie", "opp_cls": 838, "won": false, "pts": -3.0}, {"date": "26/04/2026", "opp": "MARIE Thibault", "opp_cls": 810, "won": false, "pts": -3.38}, {"date": "26/04/2026", "opp": "AUBRY Stephane", "opp_cls": 1153, "won": false, "pts": -0.38}, {"date": "26/04/2026", "opp": "LIN Lucas", "opp_cls": 750, "won": false, "pts": -3.75}, {"date": "01/03/2026", "opp": "LONG Quoc-Tien", "opp_cls": 887, "won": false, "pts": -2.25}, {"date": "01/03/2026", "opp": "PISAREK Arkadiusz", "opp_cls": 797, "won": true, "pts": 5.25}, {"date": "01/03/2026", "opp": "FANCHON Didier", "opp_cls": 602, "won": true, "pts": 2.25}, {"date": "01/03/2026", "opp": "LACERDA Gabriel", "opp_cls": 949, "won": false, "pts": -1.5}, {"date": "01/03/2026", "opp": "MAISIER Matteo", "opp_cls": 1047, "won": false, "pts": -0.75}, {"date": "01/03/2026", "opp": "LERNO Ellias", "opp_cls": 1230, "won": false, "pts": 0.0}], "solde": 15.4, "winpct": 42}, {"key": "equipe", "label": "Championnat par équipe", "V": 11, "D": 13, "pg": 33.0, "pl": -43.0, "perf": 0, "cperf": 5, "best": {"delta": -15, "opp": "SOULAS Stephane", "opp_cls": 738, "my": 753, "date": "20/03/2026", "comp": "Championnat par équipe"}, "worst": {"delta": 159, "opp": "LORRE Guillaume", "opp_cls": 592, "my": 751, "date": "12/12/2025", "comp": "Championnat par équipe"}, "matches": [{"date": "10/04/2026", "opp": "CAVIALE Laurent", "opp_cls": 1048, "won": false, "pts": -1.0}, {"date": "10/04/2026", "opp": "LE FRAPPER Romuald", "opp_cls": 1287, "won": false, "pts": 0.0}, {"date": "10/04/2026", "opp": "BOURTOUTIAN Rafi", "opp_cls": 1018, "won": false, "pts": -1.0}, {"date": "20/03/2026", "opp": "FERREIRA Eliot", "opp_cls": 985, "won": false, "pts": -1.0}, {"date": "20/03/2026", "opp": "SOULAS Stephane", "opp_cls": 738, "won": true, "pts": 6.0}, {"date": "20/03/2026", "opp": "MARTINS Enzo", "opp_cls": 748, "won": false, "pts": -5.0}, {"date": "13/02/2026", "opp": "SEMYKOZ Eduard", "opp_cls": 614, "won": false, "pts": -8.0}, {"date": "13/02/2026", "opp": "PATRY Luca Kai", "opp_cls": 611, "won": true, "pts": 4.0}, {"date": "13/02/2026", "opp": "VAYSSE Aurelien", "opp_cls": 624, "won": true, "pts": 4.0}, {"date": "06/02/2026", "opp": "DE SOUSA Alexandre", "opp_cls": 1036, "won": false, "pts": -1.0}, {"date": "06/02/2026", "opp": "WATINE Augustin", "opp_cls": 1025, "won": false, "pts": -1.0}, {"date": "06/02/2026", "opp": "MALAGAMMANA Salomé", "opp_cls": 1033, "won": false, "pts": -1.0}, {"date": "12/12/2025", "opp": "LORRE Guillaume", "opp_cls": 592, "won": false, "pts": -10.0}, {"date": "12/12/2025", "opp": "DELANDEMARE Stephane", "opp_cls": 498, "won": true, "pts": 2.0}, {"date": "12/12/2025", "opp": "SENEE Arnaud", "opp_cls": 1008, "won": false, "pts": -1.0}, {"date": "14/11/2025", "opp": "MARCO Julie", "opp_cls": 500, "won": true, "pts": 2.0}, {"date": "14/11/2025", "opp": "VOGEL Pascal", "opp_cls": 716, "won": false, "pts": -6.0}, {"date": "14/11/2025", "opp": "POIRET Celine", "opp_cls": 610, "won": true, "pts": 4.0}, {"date": "10/10/2025", "opp": "PEREIRA DESCHAMPS Adriano", "opp_cls": 567, "won": true, "pts": 3.0}, {"date": "10/10/2025", "opp": "HARDY Lény", "opp_cls": 650, "won": false, "pts": -7.0}, {"date": "10/10/2025", "opp": "YANG Xianyong", "opp_cls": 517, "won": true, "pts": 2.0}, {"date": "03/10/2025", "opp": "CIOCAN Grigore", "opp_cls": 500, "won": true, "pts": 2.0}, {"date": "03/10/2025", "opp": "ALER Christian", "opp_cls": 514, "won": true, "pts": 2.0}, {"date": "03/10/2025", "opp": "MIRANDE Monika", "opp_cls": 491, "won": true, "pts": 2.0}], "solde": -10.0, "winpct": 46, "detail": {"manches_w": 14, "manches_t": 44, "manches_pct": 32, "doubles_w": 2, "doubles_t": 4, "five": 2, "five_w": 1, "closest": {"score": "13-11", "opp": "SEMYKOZ Eduard"}, "splits": [{"team": "M11", "w": 0, "t": 6}, {"team": "M12", "w": 3, "t": 6}]}}, {"key": "criterium", "label": "Critérium fédéral", "V": 14, "D": 6, "pg": 88.5, "pl": -48.0, "perf": 2, "cperf": 3, "best": {"delta": 159, "opp": "SALAUN Pierre", "opp_cls": 879, "my": 720, "date": "19/10/2025", "comp": "Critérium fédéral"}, "worst": {"delta": 120, "opp": "JAMET Franck", "opp_cls": 622, "my": 742, "date": "25/01/2026", "comp": "Critérium fédéral"}, "matches": [{"date": "15/03/2026", "opp": "BICHOT Vincent", "opp_cls": 760, "won": false, "pts": -7.5}, {"date": "15/03/2026", "opp": "BLACODON Daniel", "opp_cls": 512, "won": true, "pts": 3.0}, {"date": "15/03/2026", "opp": "MORLEC Stéphane", "opp_cls": 485, "won": true, "pts": 3.0}, {"date": "15/03/2026", "opp": "CHILOU Christian", "opp_cls": 569, "won": true, "pts": 4.5}, {"date": "15/03/2026", "opp": "CHIRON Patrick", "opp_cls": 627, "won": true, "pts": 6.0}, {"date": "15/03/2026", "opp": "LAVAL Benjamin", "opp_cls": 715, "won": false, "pts": -9.0}, {"date": "15/03/2026", "opp": "RAIMBAULT Alexandre", "opp_cls": 739, "won": true, "pts": 9.0}, {"date": "15/03/2026", "opp": "MARQUES Emanuel", "opp_cls": 550, "won": true, "pts": 3.0}, {"date": "25/01/2026", "opp": "SINGH Vickram", "opp_cls": 626, "won": false, "pts": -12.0}, {"date": "25/01/2026", "opp": "FROGE Marc", "opp_cls": 559, "won": true, "pts": 4.5}, {"date": "25/01/2026", "opp": "DERRIEN Antoine", "opp_cls": 652, "won": true, "pts": 7.5}, {"date": "25/01/2026", "opp": "JAMET Franck", "opp_cls": 622, "won": false, "pts": -12.0}, {"date": "25/01/2026", "opp": "DUEE Pierre-Henri", "opp_cls": 518, "won": true, "pts": 3.0}, {"date": "25/01/2026", "opp": "PETRINE Diego", "opp_cls": 533, "won": true, "pts": 3.0}, {"date": "25/01/2026", "opp": "PAICHARD Yoann", "opp_cls": 663, "won": true, "pts": 7.5}, {"date": "19/10/2025", "opp": "CHAUMONT Damien", "opp_cls": 773, "won": false, "pts": -6.0}, {"date": "19/10/2025", "opp": "SALAUN Pierre", "opp_cls": 879, "won": true, "pts": 19.5}, {"date": "19/10/2025", "opp": "PATERNOTTE Cédric", "opp_cls": 592, "won": true, "pts": 6.0}, {"date": "19/10/2025", "opp": "GIGNOUX Marc", "opp_cls": 733, "won": true, "pts": 9.0}, {"date": "19/10/2025", "opp": "ALEXIS Sylvain", "opp_cls": 942, "won": false, "pts": -1.5}], "solde": 40.5, "winpct": 70}, {"key": "paris", "label": "Championnat de Paris", "V": 10, "D": 2, "pg": 33.8, "pl": -7.5, "perf": 2, "cperf": 1, "best": {"delta": 154, "opp": "BSCHORR Cedric", "opp_cls": 896, "my": 742, "date": "30/01/2026", "comp": "Championnat de Paris"}, "worst": {"delta": 185, "opp": "TSARAFIDY Alain", "opp_cls": 580, "my": 765, "date": "17/04/2026", "comp": "Championnat de Paris"}, "matches": [{"date": "15/05/2026", "opp": "FRANCK Emmanuel", "opp_cls": 655, "won": true, "pts": 3.0}, {"date": "15/05/2026", "opp": "VIVIER Patrick", "opp_cls": 634, "won": true, "pts": 3.0}, {"date": "15/05/2026", "opp": "BRUNET Christophe", "opp_cls": 515, "won": true, "pts": 1.5}, {"date": "17/04/2026", "opp": "TSARAFIDY Alain", "opp_cls": 580, "won": false, "pts": -5.25}, {"date": "17/04/2026", "opp": "NOUET Stanis", "opp_cls": 698, "won": true, "pts": 3.75}, {"date": "17/04/2026", "opp": "FRAMBOISIER Patrice", "opp_cls": 560, "won": true, "pts": 2.25}, {"date": "03/04/2026", "opp": "CARROT Sacha", "opp_cls": 539, "won": true, "pts": 1.5}, {"date": "03/04/2026", "opp": "CHAPELLE Louise", "opp_cls": 425, "won": true, "pts": 1.5}, {"date": "03/04/2026", "opp": "RAVILY Alix", "opp_cls": 559, "won": true, "pts": 2.25}, {"date": "30/01/2026", "opp": "HERON Jerome", "opp_cls": 770, "won": true, "pts": 5.25}, {"date": "30/01/2026", "opp": "SALINGARDES Marc", "opp_cls": 851, "won": false, "pts": -2.25}, {"date": "30/01/2026", "opp": "BSCHORR Cedric", "opp_cls": 896, "won": true, "pts": 9.75}], "solde": 26.3, "winpct": 83}]}