{"lic": "7523006", "nom": "LESCAUDRON", "prenom": "Noemie", "club": "08920049", "classement": {"officiel": 1085, "mensuel": 1165, "debut": 1034, "avenir": null}, "timeline": [{"m": "Sept", "v": 1034.0}, {"m": "Oct", "v": 1041.0}, {"m": "Nov", "v": 1085.0}, {"m": "Déc", "v": 1102.5}, {"m": "Janv", "v": 1089.2}, {"m": "Fév", "v": 1085.8}, {"m": "Mars", "v": 1098.8}, {"m": "Avr", "v": 1135.6}, {"m": "Mai", "v": 1143.1}, {"m": "Juin", "v": 1170.0}, {"m": "Actuel", "v": 1165, "off": true}], "saison": {"V": 87, "D": 55, "parties": 142, "winpct": 61, "perfs": 16, "contre_perfs": 22, "best": {"delta": 330, "opp": "SANDER Paul", "opp_cls": 1466, "my": 1136, "date": "04/04/2026", "comp": "Tournois"}, "worst": {"delta": 357, "opp": "GARBARG Raphaël", "opp_cls": 728, "my": 1085, "date": "28/11/2025", "comp": "Championnat par équipe"}}, "competitions": [{"key": "equipe", "label": "Championnat par équipe · Masculin", "V": 5, "D": 10, "pg": 27.0, "pl": -56.5, "perf": 2, "cperf": 5, "best": {"delta": 130, "opp": "CORAD Johann", "opp_cls": 1232, "my": 1102, "date": "12/12/2025", "comp": "Championnat par équipe · Masculin"}, "worst": {"delta": 357, "opp": "GARBARG Raphaël", "opp_cls": 728, "my": 1085, "date": "28/11/2025", "comp": "Championnat par équipe · Masculin"}, "matches": [{"date": "20/03/2026", "opp": "ZHANG Lei", "opp_cls": 1258, "won": false, "pts": -2.0}, {"date": "20/03/2026", "opp": "MABILLE Mickael", "opp_cls": 1371, "won": false, "pts": -1.0}, {"date": "20/03/2026", "opp": "DELON Sebastien", "opp_cls": 1089, "won": false, "pts": -5.0}, {"date": "13/02/2026", "opp": "LIN Haidong", "opp_cls": 911, "won": true, "pts": 3.0}, {"date": "13/02/2026", "opp": "RUSCON Romain", "opp_cls": 886, "won": true, "pts": 3.0}, {"date": "13/02/2026", "opp": "GUESPIN Eliot", "opp_cls": 1046, "won": false, "pts": -6.0}, {"date": "12/12/2025", "opp": "PETRILLI Alexandre", "opp_cls": 1003, "won": false, "pts": -7.0}, {"date": "12/12/2025", "opp": "SPRONCK Loup", "opp_cls": 1277, "won": false, "pts": -2.0}, {"date": "12/12/2025", "opp": "CORAD Johann", "opp_cls": 1232, "won": true, "pts": 10.0}, {"date": "28/11/2025", "opp": "GARBARG Raphaël", "opp_cls": 728, "won": false, "pts": -16.0}, {"date": "28/11/2025", "opp": "TIENVROT Laurent", "opp_cls": 779, "won": true, "pts": 1.0}, {"date": "28/11/2025", "opp": "CHOUKROUN Laurent", "opp_cls": 784, "won": false, "pts": -16.0}, {"date": "10/10/2025", "opp": "GALLAIS Franck", "opp_cls": 1300, "won": false, "pts": -1.0}, {"date": "10/10/2025", "opp": "STEPHANT Jean-Patrice", "opp_cls": 1141, "won": true, "pts": 10.0}, {"date": "10/10/2025", "opp": "CARIOU Romain", "opp_cls": 1383, "won": false, "pts": -0.5}], "solde": -29.5, "winpct": 33}, {"key": "equipe_f", "label": "Championnat par équipe · Féminin", "V": 30, "D": 9, "pg": 144.0, "pl": -35.5, "perf": 8, "cperf": 4, "best": {"delta": 244, "opp": "ROBINI Ines", "opp_cls": 1329, "my": 1085, "date": "15/11/2025", "comp": "Championnat par équipe · Féminin"}, "worst": {"delta": 214, "opp": "MOND Amelie", "opp_cls": 888, "my": 1102, "date": "13/12/2025", "comp": "Championnat par équipe · Féminin"}, "matches": [{"date": "06/06/2026", "opp": "ROBINI Ines", "opp_cls": 1360, "won": false, "pts": 0.0}, {"date": "06/06/2026", "opp": "BERTHAUD Marion", "opp_cls": 2016, "won": false, "pts": 0.0}, {"date": "06/06/2026", "opp": "GREMILLON-BACHELET Lilou", "opp_cls": 1189, "won": false, "pts": 0.0}, {"date": "30/05/2026", "opp": "COULAIS NOZUE Yuzuki", "opp_cls": 924, "won": true, "pts": 2.0}, {"date": "30/05/2026", "opp": "LEBOURGEOIS Lea", "opp_cls": 780, "won": true, "pts": 1.0}, {"date": "30/05/2026", "opp": "LEBOURGEOIS Aliénor", "opp_cls": 1278, "won": true, "pts": 10.0}, {"date": "11/04/2026", "opp": "SCHWITZGABEL Lara", "opp_cls": 1058, "won": true, "pts": 5.0}, {"date": "11/04/2026", "opp": "GUITEL Johanne", "opp_cls": 1044, "won": false, "pts": -7.0}, {"date": "11/04/2026", "opp": "LEFORT Emmanuelle", "opp_cls": 1016, "won": true, "pts": 4.0}, {"date": "21/03/2026", "opp": "BENAHMED Yasmine", "opp_cls": 978, "won": true, "pts": 4.0}, {"date": "21/03/2026", "opp": "ANUSHAN Angelique", "opp_cls": 1126, "won": true, "pts": 7.0}, {"date": "21/03/2026", "opp": "LEFEVRE Tessa", "opp_cls": 1077, "won": true, "pts": 6.0}, {"date": "14/02/2026", "opp": "BLEUZE Carole", "opp_cls": 890, "won": true, "pts": 3.0}, {"date": "14/02/2026", "opp": "CHAMPEIL-DESPLATS Veronique", "opp_cls": 802, "won": true, "pts": 2.0}, {"date": "14/02/2026", "opp": "CHEN Mengmeng", "opp_cls": 1357, "won": false, "pts": -1.0}, {"date": "07/02/2026", "opp": "MOINGEON Claire", "opp_cls": 1148, "won": false, "pts": -4.0}, {"date": "07/02/2026", "opp": "CHIRI Bissan", "opp_cls": 1152, "won": true, "pts": 8.0}, {"date": "07/02/2026", "opp": "BESSETTE Aurore", "opp_cls": 1008, "won": true, "pts": 5.0}, {"date": "10/01/2026", "opp": "HELLEGOUARCH Helene", "opp_cls": 838, "won": true, "pts": 2.0}, {"date": "10/01/2026", "opp": "GUITEL Johanne", "opp_cls": 1053, "won": false, "pts": -6.0}, {"date": "10/01/2026", "opp": "LEFORT Emmanuelle", "opp_cls": 1046, "won": true, "pts": 5.0}, {"date": "13/12/2025", "opp": "MOND Amelie", "opp_cls": 888, "won": false, "pts": -12.5}, {"date": "13/12/2025", "opp": "REY Valentine", "opp_cls": 1227, "won": true, "pts": 10.0}, {"date": "13/12/2025", "opp": "CHARTIER Aurelia", "opp_cls": 786, "won": true, "pts": 1.0}, {"date": "29/11/2025", "opp": "CARDOSO Jade", "opp_cls": 962, "won": true, "pts": 4.0}, {"date": "29/11/2025", "opp": "DIENG Kelly", "opp_cls": 1211, "won": true, "pts": 10.0}, {"date": "29/11/2025", "opp": "SALIN Amandine", "opp_cls": 1075, "won": false, "pts": -5.0}, {"date": "15/11/2025", "opp": "CHAMBON Apolline", "opp_cls": 770, "won": true, "pts": 1.0}, {"date": "15/11/2025", "opp": "ROBINI Ines", "opp_cls": 1329, "won": true, "pts": 17.0}, {"date": "15/11/2025", "opp": "GREMILLON-BACHELET Lilou", "opp_cls": 1027, "won": true, "pts": 5.0}, {"date": "11/10/2025", "opp": "VINCENT Lilou", "opp_cls": 881, "won": true, "pts": 3.0}, {"date": "11/10/2025", "opp": "LEBOURGEOIS Aliénor", "opp_cls": 1068, "won": true, "pts": 7.0}, {"date": "11/10/2025", "opp": "LEBOURGEOIS Lea", "opp_cls": 692, "won": true, "pts": 1.0}, {"date": "04/10/2025", "opp": "LAURIN Julie", "opp_cls": 784, "won": true, "pts": 2.0}, {"date": "04/10/2025", "opp": "ROC Aurelie", "opp_cls": 1162, "won": true, "pts": 10.0}, {"date": "04/10/2025", "opp": "MARTIN Clara", "opp_cls": 810, "won": true, "pts": 2.0}, {"date": "20/09/2025", "opp": "DE GAVRILOFF Claire", "opp_cls": 508, "won": true, "pts": 0.0}, {"date": "20/09/2025", "opp": "DOS REIS Tiphaine", "opp_cls": 862, "won": true, "pts": 3.0}, {"date": "20/09/2025", "opp": "CHENNEVIERE Natacha", "opp_cls": 892, "won": true, "pts": 4.0}], "solde": 108.5, "winpct": 77, "detail": {"manches_w": 50, "manches_t": 90, "manches_pct": 56, "doubles_w": 6, "doubles_t": 8, "five": 5, "five_w": 2, "closest": {"score": "17-15", "opp": "ANUSHAN Angelique"}, "splits": [{"team": "F1", "w": 12, "t": 18}, {"team": "M11", "w": 2, "t": 3}, {"team": "M9", "w": 0, "t": 3}]}}, {"key": "tournoi", "label": "Tournois", "V": 24, "D": 23, "pg": 79.9, "pl": -73.3, "perf": 4, "cperf": 7, "best": {"delta": 330, "opp": "SANDER Paul", "opp_cls": 1466, "my": 1136, "date": "04/04/2026", "comp": "Tournois"}, "worst": {"delta": 202, "opp": "DE ALMEIDA Terence", "opp_cls": 934, "my": 1136, "date": "04/04/2026", "comp": "Tournois"}, "matches": [{"date": "13/06/2026", "opp": "NEHME Raphael", "opp_cls": 974, "won": false, "pts": -7.5}, {"date": "13/06/2026", "opp": "RAVOUX Auguste", "opp_cls": 825, "won": true, "pts": 0.75}, {"date": "13/06/2026", "opp": "NOUBARD-PACHA Rudolphe", "opp_cls": 869, "won": true, "pts": 0.75}, {"date": "13/06/2026", "opp": "AUSSARESSES Cedric", "opp_cls": 731, "won": true, "pts": 0.38}, {"date": "13/06/2026", "opp": "LOROT Maximilien", "opp_cls": 1259, "won": false, "pts": -3.0}, {"date": "13/06/2026", "opp": "LAVINA Enzo", "opp_cls": 1476, "won": false, "pts": -0.38}, {"date": "25/05/2026", "opp": "LAPORTE Elouan", "opp_cls": 1303, "won": false, "pts": -1.5}, {"date": "25/05/2026", "opp": "TANKOUA Lucas", "opp_cls": 1142, "won": true, "pts": 4.5}, {"date": "25/05/2026", "opp": "TRILLAUD RUGGERI Marc-Antoine", "opp_cls": 1108, "won": true, "pts": 4.12}, {"date": "25/05/2026", "opp": "BOST Solen", "opp_cls": 915, "won": true, "pts": 1.5}, {"date": "25/05/2026", "opp": "PAUL Diego", "opp_cls": 1400, "won": false, "pts": -0.75}, {"date": "25/05/2026", "opp": "GNIZAKO Stephane", "opp_cls": 1015, "won": true, "pts": 3.0}, {"date": "25/05/2026", "opp": "MARCOS Ruben", "opp_cls": 1540, "won": false, "pts": -0.38}, {"date": "23/05/2026", "opp": "GAUTIE SPIREANU Daniel", "opp_cls": 1486, "won": false, "pts": -0.38}, {"date": "23/05/2026", "opp": "CARPENTIER Pascal", "opp_cls": 1060, "won": true, "pts": 3.75}, {"date": "23/05/2026", "opp": "ABDAT Enzo", "opp_cls": 1609, "won": false, "pts": 0.0}, {"date": "04/04/2026", "opp": "MANGUINE Gregory", "opp_cls": 1351, "won": false, "pts": -1.0}, {"date": "04/04/2026", "opp": "LI Max", "opp_cls": 1288, "won": false, "pts": -2.0}, {"date": "04/04/2026", "opp": "WERTHMULLER Hugo", "opp_cls": 917, "won": true, "pts": 2.0}, {"date": "04/04/2026", "opp": "POTHIER Baptiste", "opp_cls": 1150, "won": true, "pts": 6.0}, {"date": "04/04/2026", "opp": "OHANESSIAN Alexis", "opp_cls": 1104, "won": true, "pts": 5.5}, {"date": "04/04/2026", "opp": "SALMON Laurent", "opp_cls": 656, "won": true, "pts": 0.5}, {"date": "04/04/2026", "opp": "DUMERC Nicolas", "opp_cls": 1167, "won": false, "pts": -4.5}, {"date": "04/04/2026", "opp": "SANDER Paul", "opp_cls": 1466, "won": true, "pts": 22.0}, {"date": "04/04/2026", "opp": "BELHAIRE Wendy", "opp_cls": 1811, "won": false, "pts": 0.0}, {"date": "04/04/2026", "opp": "DENIS Mathilde", "opp_cls": 677, "won": true, "pts": 0.5}, {"date": "04/04/2026", "opp": "PELGAS Isabelle", "opp_cls": 434, "won": true, "pts": 0.0}, {"date": "04/04/2026", "opp": "DE ALMEIDA Terence", "opp_cls": 934, "won": false, "pts": -12.5}, {"date": "04/04/2026", "opp": "VAYSSE Léa", "opp_cls": 1141, "won": false, "pts": -5.0}, {"date": "04/04/2026", "opp": "BARRE Tommy", "opp_cls": 965, "won": true, "pts": 3.0}, {"date": "04/04/2026", "opp": "BIGNON Allan", "opp_cls": 844, "won": true, "pts": 2.0}, {"date": "04/04/2026", "opp": "DI SALVO David", "opp_cls": 700, "won": true, "pts": 0.5}, {"date": "04/04/2026", "opp": "BAALOUCHI Adam", "opp_cls": 1071, "won": false, "pts": -7.0}, {"date": "21/12/2025", "opp": "GUILLAUME Leo", "opp_cls": 1196, "won": true, "pts": 6.0}, {"date": "21/12/2025", "opp": "LESCURE Paul", "opp_cls": 1459, "won": false, "pts": -0.38}, {"date": "21/12/2025", "opp": "GUILLAUME Leo", "opp_cls": 1196, "won": false, "pts": -3.0}, {"date": "21/12/2025", "opp": "BEAUDEAU Joffrey", "opp_cls": 1158, "won": true, "pts": 6.0}, {"date": "21/12/2025", "opp": "HUANG Celia", "opp_cls": 681, "won": true, "pts": 0.38}, {"date": "21/12/2025", "opp": "SENDER Yohann", "opp_cls": 1026, "won": false, "pts": -5.25}, {"date": "21/12/2025", "opp": "DE PASCALE Dylan", "opp_cls": 1063, "won": false, "pts": -4.5}, {"date": "20/12/2025", "opp": "KUKIC Luka", "opp_cls": 1044, "won": false, "pts": -5.25}, {"date": "20/12/2025", "opp": "LESSERTISSEUR Gabin", "opp_cls": 760, "won": true, "pts": 0.75}, {"date": "20/12/2025", "opp": "CHALIER Nolan", "opp_cls": 953, "won": false, "pts": -6.0}, {"date": "20/12/2025", "opp": "NEHME Raphael", "opp_cls": 918, "won": true, "pts": 2.25}, {"date": "20/12/2025", "opp": "BRUGIER Antoine", "opp_cls": 1252, "won": false, "pts": -2.25}, {"date": "20/12/2025", "opp": "BOISSOT Gaetane", "opp_cls": 1009, "won": true, "pts": 3.75}, {"date": "20/12/2025", "opp": "PHENE Kevin", "opp_cls": 1368, "won": false, "pts": -0.75}], "solde": 6.6, "winpct": 51}, {"key": "criterium", "label": "Critérium fédéral", "V": 17, "D": 7, "pg": 88.5, "pl": -54.0, "perf": 1, "cperf": 3, "best": {"delta": 1, "opp": "FAVREUX Albanne", "opp_cls": 1042, "my": 1041, "date": "19/10/2025", "comp": "Critérium fédéral"}, "worst": {"delta": 160, "opp": "GARCIA Cassey", "opp_cls": 929, "my": 1089, "date": "25/01/2026", "comp": "Critérium fédéral"}, "matches": [{"date": "15/03/2026", "opp": "BONNEVILLE Manon", "opp_cls": 701, "won": true, "pts": 1.5}, {"date": "15/03/2026", "opp": "CHEUNG Liora", "opp_cls": 1338, "won": false, "pts": -1.5}, {"date": "15/03/2026", "opp": "NGUYEN Ema", "opp_cls": 994, "won": true, "pts": 6.0}, {"date": "15/03/2026", "opp": "DUPONT Elsa", "opp_cls": 1090, "won": true, "pts": 9.0}, {"date": "15/03/2026", "opp": "MO Milina", "opp_cls": 868, "won": true, "pts": 3.0}, {"date": "15/03/2026", "opp": "DOUCHET Anabelle", "opp_cls": 891, "won": true, "pts": 3.0}, {"date": "25/01/2026", "opp": "ANUSHAN Angelique", "opp_cls": 1032, "won": false, "pts": -9.0}, {"date": "25/01/2026", "opp": "BOUCHER Cassandra", "opp_cls": 1038, "won": true, "pts": 7.5}, {"date": "25/01/2026", "opp": "GARCIA Cassey", "opp_cls": 929, "won": false, "pts": -15.0}, {"date": "25/01/2026", "opp": "GODIN Emeline", "opp_cls": 973, "won": true, "pts": 6.0}, {"date": "25/01/2026", "opp": "DUPONT Elsa", "opp_cls": 1071, "won": true, "pts": 9.0}, {"date": "25/01/2026", "opp": "POMMAT-PERRON Lola", "opp_cls": 951, "won": false, "pts": -12.0}, {"date": "23/11/2025", "opp": "MO Milina", "opp_cls": 828, "won": true, "pts": 3.0}, {"date": "23/11/2025", "opp": "AGOSTINI Paloma", "opp_cls": 1188, "won": false, "pts": -4.5}, {"date": "23/11/2025", "opp": "GARCIA Cassey", "opp_cls": 928, "won": true, "pts": 4.5}, {"date": "23/11/2025", "opp": "LENOIR Jade", "opp_cls": 930, "won": true, "pts": 4.5}, {"date": "23/11/2025", "opp": "HUYNH Lia", "opp_cls": 831, "won": true, "pts": 3.0}, {"date": "23/11/2025", "opp": "NGUYEN Afrah", "opp_cls": 944, "won": true, "pts": 6.0}, {"date": "19/10/2025", "opp": "SONG Emma", "opp_cls": 802, "won": true, "pts": 3.0}, {"date": "19/10/2025", "opp": "GOURDON Laura", "opp_cls": 1048, "won": false, "pts": -7.5}, {"date": "19/10/2025", "opp": "GIRARD Clara", "opp_cls": 1166, "won": false, "pts": -4.5}, {"date": "19/10/2025", "opp": "FAVREUX Albanne", "opp_cls": 1042, "won": true, "pts": 9.0}, {"date": "19/10/2025", "opp": "POMMAT-PERRON Lola", "opp_cls": 972, "won": true, "pts": 7.5}, {"date": "19/10/2025", "opp": "SONG Emma", "opp_cls": 802, "won": true, "pts": 3.0}], "solde": 34.5, "winpct": 71}, {"key": "paris", "label": "Championnat de Paris", "V": 7, "D": 2, "pg": 18.4, "pl": -15.0, "perf": 0, "cperf": 2, "best": {"delta": -22, "opp": "SEYLER Damien", "opp_cls": 1067, "my": 1089, "date": "30/01/2026", "comp": "Championnat de Paris"}, "worst": {"delta": 182, "opp": "TOURELLE Marc", "opp_cls": 954, "my": 1136, "date": "17/04/2026", "comp": "Championnat de Paris"}, "matches": [{"date": "17/04/2026", "opp": "LEON Olivier", "opp_cls": 889, "won": true, "pts": 1.5}, {"date": "17/04/2026", "opp": "TOURELLE Marc", "opp_cls": 954, "won": false, "pts": -7.5}, {"date": "17/04/2026", "opp": "AMAR Frederic", "opp_cls": 876, "won": true, "pts": 1.5}, {"date": "30/01/2026", "opp": "FAUSTIN Will", "opp_cls": 1037, "won": true, "pts": 4.12}, {"date": "30/01/2026", "opp": "SEYLER Damien", "opp_cls": 1067, "won": true, "pts": 4.5}, {"date": "30/01/2026", "opp": "SCHROEDER Jimmy", "opp_cls": 1031, "won": true, "pts": 3.75}, {"date": "05/12/2025", "opp": "RONOT Philippe", "opp_cls": 833, "won": true, "pts": 1.5}, {"date": "05/12/2025", "opp": "VIEYRA Hubert Evariste", "opp_cls": 866, "won": true, "pts": 1.5}, {"date": "05/12/2025", "opp": "BOURTOUTIAN Rafi", "opp_cls": 924, "won": false, "pts": -7.5}], "solde": 3.4, "winpct": 78}], "team_levels": [{"t": "F1", "my": 1170, "opp": 1360}, {"t": "F1", "my": 1170, "opp": 2016}, {"t": "F1", "my": 1170, "opp": 1189}, {"t": "F1", "my": 1143, "opp": 924}, {"t": "F1", "my": 1143, "opp": 780}, {"t": "F1", "my": 1143, "opp": 1278}, {"t": "F1", "my": 1136, "opp": 1058}, {"t": "F1", "my": 1136, "opp": 1044}, {"t": "F1", "my": 1136, "opp": 1016}, {"t": "F1", "my": 1099, "opp": 978}, {"t": "F1", "my": 1099, "opp": 1126}, {"t": "F1", "my": 1099, "opp": 1077}, {"t": "M9", "my": 1099, "opp": 1258}, {"t": "M9", "my": 1099, "opp": 1371}, {"t": "M9", "my": 1099, "opp": 1089}, {"t": "F1", "my": 1086, "opp": 890}, {"t": "F1", "my": 1086, "opp": 802}, {"t": "F1", "my": 1086, "opp": 1357}, {"t": "M11", "my": 1086, "opp": 911}, {"t": "M11", "my": 1086, "opp": 886}, {"t": "M11", "my": 1086, "opp": 1046}, {"t": "F1", "my": 1086, "opp": 1148}, {"t": "F1", "my": 1086, "opp": 1152}, {"t": "F1", "my": 1086, "opp": 1008}, {"t": "F1", "my": 1089, "opp": 1053}, {"t": "F1", "my": 1089, "opp": 1046}, {"t": "F1", "my": 1085, "opp": 1329}, {"t": "F1", "my": 1085, "opp": 1027}, {"t": "F1", "my": 1041, "opp": 1068}, {"t": "F1", "my": 1041, "opp": 692}]}