{"lic": "9236487", "nom": "TORELLI", "prenom": "Jean-Marc", "club": "08920049", "classement": {"officiel": 874, "mensuel": 891, "debut": 900, "avenir": null}, "timeline": [{"m": "Sept", "v": 900.0}, {"m": "Oct", "v": 889.5}, {"m": "Nov", "v": 889.5}, {"m": "Déc", "v": 889.5}, {"m": "Janv", "v": 879.5}, {"m": "Fév", "v": 883.2}, {"m": "Mars", "v": 883.2}, {"m": "Avr", "v": 881.2}, {"m": "Mai", "v": 888.8}, {"m": "Juin", "v": 896.1}, {"m": "Actuel", "v": 891, "off": true}], "saison": {"V": 10, "D": 23, "parties": 33, "winpct": 30, "perfs": 1, "contre_perfs": 3, "best": {"delta": 17, "opp": "DIAS Sebastien", "opp_cls": 906, "my": 889, "date": "24/05/2026", "comp": "Tournois"}, "worst": {"delta": 152, "opp": "DOS SANTOS-LHOSTE Alexandre", "opp_cls": 738, "my": 890, "date": "12/12/2025", "comp": "Championnat par équipe"}}, "competitions": [{"key": "equipe", "label": "Championnat par équipe", "V": 1, "D": 17, "pg": 6.0, "pl": -32.0, "perf": 0, "cperf": 2, "best": {"delta": -8, "opp": "NAIM Axel", "opp_cls": 881, "my": 890, "date": "12/12/2025", "comp": "Championnat par équipe"}, "worst": {"delta": 152, "opp": "DOS SANTOS-LHOSTE Alexandre", "opp_cls": 738, "my": 890, "date": "12/12/2025", "comp": "Championnat par équipe"}, "matches": [{"date": "05/06/2026", "opp": "LOPES Andre", "opp_cls": 1436, "won": false, "pts": 0.0}, {"date": "05/06/2026", "opp": "GAUTHRON Henri", "opp_cls": 946, "won": false, "pts": 0.0}, {"date": "05/06/2026", "opp": "RICART Franck", "opp_cls": 1479, "won": false, "pts": 0.0}, {"date": "29/05/2026", "opp": "MOREAUX Dimitri", "opp_cls": 1359, "won": false, "pts": 0.0}, {"date": "29/05/2026", "opp": "BOYER Hugo", "opp_cls": 1131, "won": false, "pts": -1.0}, {"date": "29/05/2026", "opp": "MONJO Luc", "opp_cls": 1421, "won": false, "pts": 0.0}, {"date": "08/05/2026", "opp": "COURTOIS Pierre", "opp_cls": 1094, "won": false, "pts": -1.0}, {"date": "08/05/2026", "opp": "CHAMBON Amelie", "opp_cls": 1241, "won": false, "pts": -0.5}, {"date": "08/05/2026", "opp": "DAS NEVES Alef higor", "opp_cls": 1180, "won": false, "pts": -1.0}, {"date": "20/03/2026", "opp": "LE SAOS Cedric", "opp_cls": 1140, "won": false, "pts": -1.0}, {"date": "20/03/2026", "opp": "LIU Justin", "opp_cls": 1252, "won": false, "pts": -0.5}, {"date": "20/03/2026", "opp": "D HAULTFOEUILLE-MIMOUNI Alexandre", "opp_cls": 1282, "won": false, "pts": -0.5}, {"date": "12/12/2025", "opp": "KESBY Yann", "opp_cls": 850, "won": false, "pts": -6.0}, {"date": "12/12/2025", "opp": "DOS SANTOS-LHOSTE Alexandre", "opp_cls": 738, "won": false, "pts": -10.0}, {"date": "12/12/2025", "opp": "NAIM Axel", "opp_cls": 881, "won": true, "pts": 6.0}, {"date": "19/09/2025", "opp": "DUCOUDRAY Antonin", "opp_cls": 912, "won": false, "pts": -7.0}, {"date": "19/09/2025", "opp": "MOREAUX Dimitri", "opp_cls": 1274, "won": false, "pts": -0.5}, {"date": "19/09/2025", "opp": "RENET Jean-Baptiste", "opp_cls": 1006, "won": false, "pts": -3.0}], "solde": -26.0, "winpct": 6, "detail": {"manches_w": 11, "manches_t": 47, "manches_pct": 23, "doubles_w": 0, "doubles_t": 4, "five": 3, "five_w": 0, "closest": {"score": "13-11", "opp": "GAUTHRON Henri"}, "splits": [{"team": "M6", "w": 0, "t": 12}]}}, {"key": "tournoi", "label": "Tournois", "V": 4, "D": 5, "pg": 11.6, "pl": -0.8, "perf": 1, "cperf": 0, "best": {"delta": 17, "opp": "DIAS Sebastien", "opp_cls": 906, "my": 889, "date": "24/05/2026", "comp": "Tournois"}, "worst": {"delta": -300, "opp": "ZHANG David", "opp_cls": 1189, "my": 889, "date": "24/05/2026", "comp": "Tournois"}, "matches": [{"date": "24/05/2026", "opp": "FLORENTIN Clément", "opp_cls": 1202, "won": false, "pts": -0.38}, {"date": "24/05/2026", "opp": "AUSSARESSES Cedric", "opp_cls": 848, "won": true, "pts": 4.12}, {"date": "24/05/2026", "opp": "NIE Kevin", "opp_cls": 652, "won": true, "pts": 1.5}, {"date": "24/05/2026", "opp": "DIAS Sebastien", "opp_cls": 906, "won": true, "pts": 4.5}, {"date": "24/05/2026", "opp": "RIOULT Gabriel", "opp_cls": 652, "won": true, "pts": 1.5}, {"date": "24/05/2026", "opp": "ZHANG David", "opp_cls": 1189, "won": false, "pts": -0.38}, {"date": "24/05/2026", "opp": "BARLOT-LAHAYE Nathan", "opp_cls": 1336, "won": false, "pts": 0.0}, {"date": "23/05/2026", "opp": "LMACHICHI Ziad", "opp_cls": 1424, "won": false, "pts": 0.0}, {"date": "23/05/2026", "opp": "AUDRAIN Baptiste", "opp_cls": 1420, "won": false, "pts": 0.0}], "solde": 10.8, "winpct": 44}, {"key": "paris", "label": "Championnat de Paris", "V": 5, "D": 1, "pg": 15.0, "pl": -3.8, "perf": 0, "cperf": 1, "best": {"delta": -52, "opp": "BRONDEL Pascal", "opp_cls": 828, "my": 880, "date": "16/01/2026", "comp": "Championnat de Paris"}, "worst": {"delta": 6, "opp": "MARKOVIC Deyan", "opp_cls": 874, "my": 880, "date": "16/01/2026", "comp": "Championnat de Paris"}, "matches": [{"date": "03/04/2026", "opp": "RIDOR Raphaël", "opp_cls": 752, "won": true, "pts": 3.0}, {"date": "03/04/2026", "opp": "SAMPAIO Alex", "opp_cls": 572, "won": true, "pts": 0.75}, {"date": "03/04/2026", "opp": "VILMANT Laurent", "opp_cls": 787, "won": true, "pts": 3.75}, {"date": "16/01/2026", "opp": "MARKOVIC Deyan", "opp_cls": 874, "won": false, "pts": -3.75}, {"date": "16/01/2026", "opp": "BRONDEL Pascal", "opp_cls": 828, "won": true, "pts": 3.75}, {"date": "16/01/2026", "opp": "DUBOIS Jean Luc", "opp_cls": 787, "won": true, "pts": 3.75}], "solde": 11.2, "winpct": 83}], "team_levels": [{"t": "M6", "my": 896, "opp": 1436}, {"t": "M6", "my": 896, "opp": 946}, {"t": "M6", "my": 896, "opp": 1479}, {"t": "M6", "my": 889, "opp": 1359}, {"t": "M6", "my": 889, "opp": 1131}, {"t": "M6", "my": 889, "opp": 1421}, {"t": "M6", "my": 889, "opp": 1094}, {"t": "M6", "my": 889, "opp": 1241}, {"t": "M6", "my": 889, "opp": 1180}, {"t": "M6", "my": 883, "opp": 1140}, {"t": "M6", "my": 883, "opp": 1252}, {"t": "M6", "my": 883, "opp": 1282}, {"t": "M6", "my": 900, "opp": 1274}]}