{"division": "L08_2eme Division Poule 16", "organisme": "16", "phase": "1", "poule": 5, "cx_poule": 1157390, "classement": [{"clt": "1", "equipe": "BOIS COLOMBES S (4)", "pts": "21", "joue": "7", "vic": "7", "nul": "0", "def": "0", "pg": "297", "pp": "143"}, {"clt": "2", "equipe": "ADAMOIS TT (2)", "pts": "17", "joue": "7", "vic": "5", "nul": "0", "def": "2", "pg": "242", "pp": "153"}, {"clt": "3", "equipe": "DOMONT TT (2)", "pts": "15", "joue": "7", "vic": "4", "nul": "0", "def": "3", "pg": "248", "pp": "193"}, {"clt": "4", "equipe": "CPS 10eme 2", "pts": "15", "joue": "7", "vic": "4", "nul": "0", "def": "3", "pg": "225", "pp": "213"}, {"clt": "5", "equipe": "MERY US TT (3)", "pts": "13", "joue": "7", "vic": "3", "nul": "0", "def": "4", "pg": "208", "pp": "230"}, {"clt": "6", "equipe": "TAVERNY TT  (2)", "pts": "11", "joue": "7", "vic": "2", "nul": "0", "def": "5", "pg": "208", "pp": "233"}, {"clt": "7", "equipe": "BESSANCOURT TTB (3)", "pts": "11", "joue": "7", "vic": "2", "nul": "0", "def": "5", "pg": "183", "pp": "258"}, {"clt": "8", "equipe": "AUBERVILLIERS CMTT (1)", "pts": "8", "joue": "7", "vic": "1", "nul": "0", "def": "5", "pg": "101", "pp": "289"}], "rencontres": [{"date": "05/12/2025", "equa": "CPS 10eme 2", "equb": "ADAMOIS TT (2)", "scorea": "24", "scoreb": "39", "compo_a": [{"nom": "HART Gabriel", "pts": 707}, {"nom": "FISCHER Laurent", "pts": 905}, {"nom": "LIN Léo", "pts": 588}], "compo_b": [{"nom": "TEIXEIRA Enzo", "pts": 1312}, {"nom": "RAVENAZ Xavier", "pts": 1103}, {"nom": "GULAM Steve", "pts": 500}]}, {"date": "05/12/2025", "equa": "MERY US TT (3)", "equb": "DOMONT TT (2)", "scorea": "9", "scoreb": "54", "compo_a": [{"nom": "DELPLACE Brian", "pts": 500}, {"nom": "MIELLE Cedric", "pts": 726}, {"nom": "LE Thomas Alexandre", "pts": 500}], "compo_b": [{"nom": "ORLANDINI Christophe", "pts": 843}, {"nom": "MARCONNET Philippe", "pts": 769}, {"nom": "DESVIGNES Pascal", "pts": 670}]}, {"date": "05/12/2025", "equa": "BESSANCOURT TTB (3)", "equb": "BOIS COLOMBES S (4)", "scorea": "29", "scoreb": "34", "compo_a": [{"nom": "MASSACRIER Daniel", "pts": 694}, {"nom": "SMITH Eliott", "pts": 680}, {"nom": "GARBANI LECOURT Alexis", "pts": 699}], "compo_b": [{"nom": "COSTES Pierre", "pts": 712}, {"nom": "KARRER Remy", "pts": 719}, {"nom": "THOMAS Noa", "pts": 624}]}, {"date": "05/12/2025", "equa": "TAVERNY TT  (2)", "equb": "AUBERVILLIERS CMTT (1)", "scorea": "29", "scoreb": "34", "compo_a": [{"nom": "CHAUVIN Claire", "pts": 705}, {"nom": "SALMON Laurent", "pts": 635}, {"nom": "PICARD Cedric", "pts": 826}], "compo_b": [{"nom": "EPAIN Joseph", "pts": 524}, {"nom": "MOLARD Mathieu", "pts": 840}, {"nom": "VEYSSIER Clement", "pts": 701}]}, {"date": "16/01/2026", "equa": "DOMONT TT (2)", "equb": "CPS 10eme 2", "scorea": "44", "scoreb": "19", "compo_a": [{"nom": "MARCONNET Philippe", "pts": 769}, {"nom": "ORLANDINI Christophe", "pts": 843}, {"nom": "DESVIGNES Pascal", "pts": 670}], "compo_b": [{"nom": "REBONDY Aurelien", "pts": 607}, {"nom": "BRUANDET Pascal", "pts": 500}, {"nom": "BRAILLARD Arthur", "pts": 572}]}, {"date": "16/01/2026", "equa": "BOIS COLOMBES S (4)", "equb": "MERY US TT (3)", "scorea": "44", "scoreb": "19", "compo_a": [{"nom": "LARBRE Jean-Pascal", "pts": 694}, {"nom": "LUPPINO Ludovic", "pts": 733}, {"nom": "EPHIMENCO Maxime", "pts": 736}], "compo_b": [{"nom": "VINCENT Thierry", "pts": 914}, {"nom": "DELPLACE Brian", "pts": 500}, {"nom": "BAROUH Roland", "pts": 693}]}, {"date": "16/01/2026", "equa": "AUBERVILLIERS CMTT (1)", "equb": "BESSANCOURT TTB (3)", "scorea": "19", "scoreb": "44", "compo_a": [{"nom": "RENAUD Killian", "pts": 500}, {"nom": "SARKAR Debankan", "pts": 500}, {"nom": "DESHAYES Camilla", "pts": 500}], "compo_b": [{"nom": "AHONZO Cheickna", "pts": 657}, {"nom": "SOAVE Theo", "pts": 582}, {"nom": "SOAVE Christian", "pts": 548}]}, {"date": "16/01/2026", "equa": "ADAMOIS TT (2)", "equb": "TAVERNY TT  (2)", "scorea": "34", "scoreb": "29", "compo_a": [{"nom": "MJID Wissem", "pts": 1428}, {"nom": "GULAM Steve", "pts": 500}, {"nom": "GLANDIERES-CASTILLO Martin", "pts": 1110}], "compo_b": [{"nom": "SALMON Aurelien", "pts": 1100}, {"nom": "GUILLERD Maximilien", "pts": 1066}, {"nom": "FERRANDIS Frederic", "pts": 1108}]}, {"date": "30/01/2026", "equa": "CPS 10eme 2", "equb": "BOIS COLOMBES S (4)", "scorea": "9", "scoreb": "54", "compo_a": [{"nom": "BRUANDET Pascal", "pts": 500}, {"nom": "BUISSON Bruno", "pts": 500}, {"nom": "FRAYSSINET Jean-Vincent", "pts": 520}], "compo_b": [{"nom": "LARBRE Jean-Pascal", "pts": 694}, {"nom": "KARRER Remy", "pts": 719}, {"nom": "EPHIMENCO Maxime", "pts": 736}]}, {"date": "30/01/2026", "equa": "MERY US TT (3)", "equb": "AUBERVILLIERS CMTT (1)", "scorea": "54", "scoreb": "6", "compo_a": [{"nom": "DELPLACE Brian", "pts": 500}, {"nom": "LE Thomas Alexandre", "pts": 500}, {"nom": "BERTHEUIL Edgar", "pts": 574}], "compo_b": [{"nom": "RENAUD Killian", "pts": 500}, {"nom": "DESHAYES Camilla", "pts": 500}]}, {"date": "30/01/2026", "equa": "BESSANCOURT TTB (3)", "equb": "TAVERNY TT  (2)", "scorea": "39", "scoreb": "24", "compo_a": [{"nom": "SOAVE Christian", "pts": 548}, {"nom": "VICTOR Thierry", "pts": 786}, {"nom": "SMITH Nicolas", "pts": 759}], "compo_b": [{"nom": "ONESIME Alain", "pts": 662}, {"nom": "CHAUVIN Claire", "pts": 705}, {"nom": "SALMON Laurent", "pts": 635}]}, {"date": "30/01/2026", "equa": "ADAMOIS TT (2)", "equb": "DOMONT TT (2)", "scorea": "54", "scoreb": "9", "compo_a": [{"nom": "GLANDIERES-CASTILLO Martin", "pts": 1110}, {"nom": "TEIXEIRA Enzo", "pts": 1312}, {"nom": "LONGHI Julien", "pts": 1273}], "compo_b": [{"nom": "DESVIGNES Pascal", "pts": 670}, {"nom": "ORLANDINI Christophe", "pts": 843}, {"nom": "ANGERVILLE Mathis", "pts": 1332}]}, {"date": "27/03/2026", "equa": "AUBERVILLIERS CMTT (1)", "equb": "CPS 10eme 2", "scorea": "24", "scoreb": "36", "compo_a": [{"nom": "CERTAIN Laura", "pts": 500}, {"nom": "MAZERAND TEMZI Lynda", "pts": 500}, {"nom": "SARKAR Debankan", "pts": 500}], "compo_b": [{"nom": "BUISSON Bruno", "pts": 500}, {"nom": "CHANNA Riddhima", "pts": 543}]}, {"date": "27/03/2026", "equa": "TAVERNY TT  (2)", "equb": "MERY US TT (3)", "scorea": "44", "scoreb": "19", "compo_a": [{"nom": "DESBROSSE Olivier", "pts": 836}, {"nom": "PICARD Cedric", "pts": 826}, {"nom": "CHAUVIN Claire", "pts": 705}], "compo_b": [{"nom": "LE TENNIER Julien", "pts": 629}, {"nom": "RUBIO Loann", "pts": 682}, {"nom": "PANISSIER Quentin", "pts": 719}]}, {"date": "27/03/2026", "equa": "BESSANCOURT TTB (3)", "equb": "ADAMOIS TT (2)", "scorea": "24", "scoreb": "39", "compo_a": [{"nom": "GARBANI Fabrice", "pts": 770}, {"nom": "AHONZO Cheickna", "pts": 657}, {"nom": "SOAVE Christian", "pts": 548}], "compo_b": [{"nom": "GLANDIERES-CASTILLO Martin", "pts": 1110}, {"nom": "RAVENAZ Xavier", "pts": 1103}, {"nom": "BANAGA-BOYOMO Joris", "pts": 500}]}, {"date": "27/03/2026", "equa": "BOIS COLOMBES S (4)", "equb": "DOMONT TT (2)", "scorea": "34", "scoreb": "29", "compo_a": [{"nom": "EPHIMENCO Maxime", "pts": 736}, {"nom": "THOMAS Noa", "pts": 624}, {"nom": "LUPPINO Ludovic", "pts": 733}], "compo_b": [{"nom": "ANGERVILLE Mathis", "pts": 1332}, {"nom": "ORLANDINI Christophe", "pts": 843}, {"nom": "DESVIGNES Pascal", "pts": 670}]}, {"date": "03/04/2026", "equa": "CPS 10eme 2", "equb": "TAVERNY TT  (2)", "scorea": "49", "scoreb": "14", "compo_a": [{"nom": "SLIMANE Tristan", "pts": 936}, {"nom": "FISCHER Laurent", "pts": 905}, {"nom": "BELLANGER David", "pts": 860}], "compo_b": [{"nom": "PRIMOT Christophe", "pts": 918}, {"nom": "PICARD Cedric", "pts": 826}, {"nom": "ONESIME Alain", "pts": 662}]}, {"date": "03/04/2026", "equa": "MERY US TT (3)", "equb": "BESSANCOURT TTB (3)", "scorea": "49", "scoreb": "14", "compo_a": [{"nom": "LE TENNIER Julien", "pts": 629}, {"nom": "RUBIO Loann", "pts": 682}, {"nom": "JOUANNET Sophie", "pts": 801}], "compo_b": [{"nom": "AHONZO Cheickna", "pts": 657}, {"nom": "SOAVE Christian", "pts": 548}, {"nom": "PARISSE Philippe", "pts": 500}]}, {"date": "03/04/2026", "equa": "DOMONT TT (2)", "equb": "AUBERVILLIERS CMTT (1)", "scorea": "54", "scoreb": "9", "compo_a": [{"nom": "DESVIGNES Pascal", "pts": 670}, {"nom": "ORLANDINI Christophe", "pts": 843}, {"nom": "MARCONNET Philippe", "pts": 769}], "compo_b": [{"nom": "MILOSEVIC Jovan", "pts": 500}, {"nom": "RENAUD Killian", "pts": 500}, {"nom": "DESHAYES Camilla", "pts": 500}]}, {"date": "03/04/2026", "equa": "ADAMOIS TT (2)", "equb": "BOIS COLOMBES S (4)", "scorea": "29", "scoreb": "33", "compo_a": [{"nom": "MJID Wissem", "pts": 1428}, {"nom": "GLANDIERES-CASTILLO Martin", "pts": 1110}, {"nom": "RAVENAZ Xavier", "pts": 1103}], "compo_b": [{"nom": "WATZKO Frédéric", "pts": 1694}, {"nom": "ENJOLRAS Guillaume", "pts": 1284}, {"nom": "HUYNH Michel", "pts": 1112}]}, {"date": "17/04/2026", "equa": "BESSANCOURT TTB (3)", "equb": "CPS 10eme 2", "scorea": "14", "scoreb": "49", "compo_a": [{"nom": "MICHELOT Alexis", "pts": 599}, {"nom": "SOAVE Christian", "pts": 548}, {"nom": "PARISSE Philippe", "pts": 500}], "compo_b": [{"nom": "REBONDY Aurelien", "pts": 607}, {"nom": "PERTUS Adrien", "pts": 775}, {"nom": "HART Gabriel", "pts": 707}]}, {"date": "17/04/2026", "equa": "MERY US TT (3)", "equb": "ADAMOIS TT (2)", "scorea": "34", "scoreb": "29", "compo_a": [{"nom": "BRONDY Christian", "pts": 500}, {"nom": "PERRIN Jean-François", "pts": 782}, {"nom": "BARBESANGE Theo", "pts": 500}], "compo_b": [{"nom": "TEIXEIRA Enzo", "pts": 1312}, {"nom": "PLANTECOSTE Laurent", "pts": 517}, {"nom": "DOLFI Stephane", "pts": 544}]}, {"date": "17/04/2026", "equa": "TAVERNY TT  (2)", "equb": "DOMONT TT (2)", "scorea": "49", "scoreb": "14", "compo_a": [{"nom": "PICARD Cedric", "pts": 826}, {"nom": "LEFEVRE Eric", "pts": 1153}, {"nom": "MIQUEL Joseph", "pts": 1055}], "compo_b": [{"nom": "MARCONNET Philippe", "pts": 769}, {"nom": "ORLANDINI Christophe", "pts": 843}, {"nom": "DESVIGNES Pascal", "pts": 670}]}, {"date": "17/04/2026", "equa": "AUBERVILLIERS CMTT (1)", "equb": "BOIS COLOMBES S (4)", "scorea": "9", "scoreb": "54", "compo_a": [{"nom": "DESHAYES Camilla", "pts": 500}, {"nom": "MAZERAND TEMZI Lynda", "pts": 500}, {"nom": "RENAUD Killian", "pts": 500}], "compo_b": [{"nom": "LARBRE Jean-Pascal", "pts": 694}, {"nom": "COSTES Pierre", "pts": 712}, {"nom": "KARRER Remy", "pts": 719}]}, {"date": "15/05/2026", "equa": "CPS 10eme 2", "equb": "MERY US TT (3)", "scorea": "39", "scoreb": "24", "compo_a": [{"nom": "CHANNA Riddhima", "pts": 543}, {"nom": "GRYNBERG Bernard", "pts": 611}, {"nom": "JOLY Julien", "pts": 781}], "compo_b": [{"nom": "RUBIO Loann", "pts": 682}, {"nom": "BERTHEUIL Edgar", "pts": 574}, {"nom": "LE Thomas Alexandre", "pts": 500}]}, {"date": "15/05/2026", "equa": "DOMONT TT (2)", "equb": "BESSANCOURT TTB (3)", "scorea": "44", "scoreb": "19", "compo_a": [{"nom": "ANGERVILLE Mathis", "pts": 1332}, {"nom": "DESVIGNES Pascal", "pts": 670}, {"nom": "ORLANDINI Christophe", "pts": 843}], "compo_b": [{"nom": "SOAVE Christian", "pts": 548}, {"nom": "GARBANI LECOURT Alexis", "pts": 699}, {"nom": "PARISSE Philippe", "pts": 500}]}, {"date": "15/05/2026", "equa": "BOIS COLOMBES S (4)", "equb": "TAVERNY TT  (2)", "scorea": "44", "scoreb": "19", "compo_a": [{"nom": "COSTES Pierre", "pts": 712}, {"nom": "LUPPINO Ludovic", "pts": 733}, {"nom": "LARBRE Jean-Pascal", "pts": 694}], "compo_b": [{"nom": "ZHANG Hugo", "pts": 550}, {"nom": "PICARD Cedric", "pts": 826}, {"nom": "PRIMOT Christophe", "pts": 918}]}, {"date": "15/05/2026", "equa": "ADAMOIS TT (2)", "equb": "AUBERVILLIERS CMTT (1)", "scorea": "18", "scoreb": "0", "compo_a": [{"nom": "TEIXEIRA Enzo", "pts": 1312}, {"nom": "GLANDIERES-CASTILLO Martin", "pts": 1110}, {"nom": "RAVENAZ Xavier", "pts": 1103}], "compo_b": []}]}