{"club": "STADE DE VANVES", "numero": "08921316", "joueurs": [{"lic": "9257416", "nom": "AIRAULT", "prenom": "Axel", "points": "500", "clglob": ""}, {"lic": "9263697", "nom": "AIT OUARET", "prenom": "Billel", "points": "500", "clglob": ""}, {"lic": "9261933", "nom": "ALFROID", "prenom": "Joseph", "points": "500", "clglob": ""}, {"lic": "9259401", "nom": "ALGUEMI DE QUEYLARD", "prenom": "Yann", "points": "500", "clglob": ""}, {"lic": "9263898", "nom": "ALIOUANE-BORVON", "prenom": "Anna", "points": "500", "clglob": ""}, {"lic": "9263868", "nom": "ALIX", "prenom": "Andrea", "points": "500", "clglob": ""}, {"lic": "9263875", "nom": "ALVES JUNG", "prenom": "Thibault", "points": "500", "clglob": ""}, {"lic": "9262799", "nom": "BADUEL", "prenom": "Philippe", "points": "500", "clglob": ""}, {"lic": "9266630", "nom": "BARATON", "prenom": "Inès", "points": "500", "clglob": ""}, {"lic": "7880016", "nom": "BAUBION", "prenom": "Jean", "points": "500", "clglob": ""}, {"lic": "9263857", "nom": "BENABDELHAK", "prenom": "Anthony", "points": "500", "clglob": ""}, {"lic": "9261939", "nom": "BENKEMOUN", "prenom": "Michel", "points": "500", "clglob": ""}, {"lic": "9261941", "nom": "BERRIRI", "prenom": "Abel", "points": "500", "clglob": ""}, {"lic": "9263866", "nom": "BERTON", "prenom": "Samuel", "points": "500", "clglob": ""}, {"lic": "9261943", "nom": "BOULAY", "prenom": "Mikaël", "points": "500", "clglob": ""}, {"lic": "9257470", "nom": "BOURGEOIS", "prenom": "Pierre-André", "points": "500", "clglob": ""}, {"lic": "9266631", "nom": "BRAS", "prenom": "Esteban", "points": "500", "clglob": ""}, {"lic": "9266673", "nom": "BUGAUD", "prenom": "Victor", "points": "500", "clglob": ""}, {"lic": "9263882", "nom": "CAHEN", "prenom": "Timothée", "points": "500", "clglob": ""}, {"lic": "9266632", "nom": "CAYOL", "prenom": "Marius", "points": "500", "clglob": ""}, {"lic": "9267405", "nom": "CAZENAVE", "prenom": "Baptiste", "points": "500", "clglob": ""}, {"lic": "9263870", "nom": "CHANOINE", "prenom": "Raphael", "points": "500", "clglob": ""}, {"lic": "9263912", "nom": "CHASLERIES", "prenom": "Lucas", "points": "500", "clglob": ""}, {"lic": "9266633", "nom": "CHATEL", "prenom": "Paul", "points": "500", "clglob": ""}, {"lic": "9261908", "nom": "CHEN", "prenom": "Jeremy", "points": "500", "clglob": ""}, {"lic": "9259528", "nom": "CHETTAB", "prenom": "Anis", "points": "500", "clglob": ""}, {"lic": "9263897", "nom": "CHIP", "prenom": "Aurélien", "points": "500", "clglob": ""}, {"lic": "9263904", "nom": "CHOLET", "prenom": "Timothée", "points": "500", "clglob": ""}, {"lic": "9266634", "nom": "COHEN LOUTATY", "prenom": "Zac", "points": "500", "clglob": ""}, {"lic": "9261909", "nom": "CONSONNI", "prenom": "Amedeo", "points": "500", "clglob": ""}, {"lic": "9263908", "nom": "CONSONNI", "prenom": "Ugo", "points": "500", "clglob": ""}, {"lic": "9266674", "nom": "COSTER", "prenom": "Charles", "points": "500", "clglob": ""}, {"lic": "9266886", "nom": "COSTER", "prenom": "Clément", "points": "500", "clglob": ""}, {"lic": "7510924", "nom": "COTTE", "prenom": "Francois", "points": "500", "clglob": ""}, {"lic": "9263894", "nom": "COURTEILLE", "prenom": "Diego", "points": "500", "clglob": ""}, {"lic": "9265042", "nom": "D'ALMEIDA", "prenom": "Henri", "points": "500", "clglob": ""}, {"lic": "9263861", "nom": "DADOUN", "prenom": "Eden", "points": "500", "clglob": ""}, {"lic": "9261945", "nom": "DARET", "prenom": "Hugo", "points": "500", "clglob": ""}, {"lic": "9266635", "nom": "DECROCQ", "prenom": "Mikaïl", "points": "500", "clglob": ""}, {"lic": "9261947", "nom": "DEGEETER VILLIERS", "prenom": "Maëlle", "points": "500", "clglob": ""}, {"lic": "9263876", "nom": "DELAHAYE", "prenom": "Fabien", "points": "500", "clglob": ""}, {"lic": "9263829", "nom": "DELAHAYE-ROUVIERE", "prenom": "Nathalie", "points": "500", "clglob": ""}, {"lic": "9266885", "nom": "DEMENTHON JAFFRE", "prenom": "Arthur", "points": "500", "clglob": ""}, {"lic": "9266636", "nom": "DENIAU", "prenom": "Romuald", "points": "500", "clglob": ""}, {"lic": "9263859", "nom": "DESHAYES-GUILHEN", "prenom": "Vasco", "points": "500", "clglob": ""}, {"lic": "9263699", "nom": "DESVEAUX CAPORAL", "prenom": "Nino", "points": "500", "clglob": ""}, {"lic": "9263903", "nom": "DIONNET CHANDELLIER", "prenom": "Arthur", "points": "500", "clglob": ""}, {"lic": "9266637", "nom": "DIONNET CHANDELLIER", "prenom": "Victor", "points": "500", "clglob": ""}, {"lic": "9257437", "nom": "DORVAL", "prenom": "Lucas", "points": "500", "clglob": ""}, {"lic": "9266639", "nom": "DOUSSOT", "prenom": "Alexis", "points": "500", "clglob": ""}, {"lic": "9243249", "nom": "DROUINEAU", "prenom": "Theo", "points": "911", "clglob": ""}, {"lic": "9263860", "nom": "DRUETTI", "prenom": "Louis", "points": "500", "clglob": ""}, {"lic": "9263889", "nom": "DUPE", "prenom": "Valentin", "points": "500", "clglob": ""}, {"lic": "9266675", "nom": "DUPIEUX", "prenom": "Joris", "points": "500", "clglob": ""}, {"lic": "9257439", "nom": "DUPRAT", "prenom": "Gaël", "points": "500", "clglob": ""}, {"lic": "9261949", "nom": "DURAND", "prenom": "Gueorgui", "points": "500", "clglob": ""}, {"lic": "9264384", "nom": "EBOSSA-RELIWA", "prenom": "Ramien", "points": "500", "clglob": ""}, {"lic": "9267404", "nom": "ECHEGARAY", "prenom": "Lucas", "points": "500", "clglob": ""}, {"lic": "9259478", "nom": "FAROUX", "prenom": "Aubin", "points": "500", "clglob": ""}, {"lic": "9261910", "nom": "FAYEMENDY", "prenom": "Laurent", "points": "500", "clglob": ""}, {"lic": "9266638", "nom": "FELLOUS", "prenom": "Eric", "points": "500", "clglob": ""}, {"lic": "9257443", "nom": "FERNANDES", "prenom": "Ruben", "points": "500", "clglob": ""}, {"lic": "9266640", "nom": "FIGUEROA", "prenom": "Thibaud", "points": "500", "clglob": ""}, {"lic": "9265040", "nom": "FLAVIGNY", "prenom": "Thierry", "points": "500", "clglob": ""}, {"lic": "9266676", "nom": "FONTY", "prenom": "Arthur", "points": "500", "clglob": ""}, {"lic": "9267409", "nom": "GERASHCHENKO", "prenom": "Kyrylo", "points": "500", "clglob": ""}, {"lic": "9263878", "nom": "GHERABA", "prenom": "Ania", "points": "500", "clglob": ""}, {"lic": "9266677", "nom": "GHERABA", "prenom": "Sofia", "points": "500", "clglob": ""}, {"lic": "9251350", "nom": "GIRAUD", "prenom": "Bertrand", "points": "500", "clglob": ""}, {"lic": "9265041", "nom": "GONZAGUE", "prenom": "Tidiane", "points": "500", "clglob": ""}, {"lic": "9251827", "nom": "GOULUT", "prenom": "Antoine", "points": "500", "clglob": ""}, {"lic": "307692", "nom": "GRANDJEAN", "prenom": "Thibau", "points": "754", "clglob": ""}, {"lic": "9266678", "nom": "GRANGER", "prenom": "Antoine", "points": "500", "clglob": ""}, {"lic": "9266680", "nom": "GUESSAD", "prenom": "Ashym", "points": "500", "clglob": ""}, {"lic": "9251905", "nom": "GUITARD", "prenom": "Arnaud", "points": "500", "clglob": ""}, {"lic": "9250653", "nom": "HERISSON", "prenom": "Alexandre", "points": "626", "clglob": ""}, {"lic": "9257446", "nom": "HOUISSA", "prenom": "Elyes", "points": "564", "clglob": ""}, {"lic": "9257500", "nom": "HOUISSA", "prenom": "Hichem", "points": "500", "clglob": ""}, {"lic": "9264098", "nom": "HOUSSET ZHANG", "prenom": "Alexis", "points": "500", "clglob": ""}, {"lic": "9252109", "nom": "HUIN", "prenom": "Olivier", "points": "636", "clglob": ""}, {"lic": "9266681", "nom": "ICOLE", "prenom": "Gabriel", "points": "500", "clglob": ""}, {"lic": "9266682", "nom": "ICOLE", "prenom": "Nathanaël", "points": "500", "clglob": ""}, {"lic": "9264385", "nom": "JAUFFRET", "prenom": "Vincent", "points": "500", "clglob": ""}, {"lic": "9259488", "nom": "JEAN", "prenom": "Dodly", "points": "578", "clglob": ""}, {"lic": "9263883", "nom": "JEBALI", "prenom": "Adam", "points": "500", "clglob": ""}, {"lic": "9263900", "nom": "JILIBERT", "prenom": "Gaël", "points": "500", "clglob": ""}, {"lic": "9264101", "nom": "JOURNEL", "prenom": "Arthur", "points": "500", "clglob": ""}, {"lic": "9263905", "nom": "JOURNEL", "prenom": "Lucas", "points": "500", "clglob": ""}, {"lic": "9257448", "nom": "JUTIGNY", "prenom": "Martin", "points": "500", "clglob": ""}, {"lic": "9257449", "nom": "JUTIGNY", "prenom": "Oscar", "points": "500", "clglob": ""}, {"lic": "9259489", "nom": "KHOUALEF", "prenom": "Yacine", "points": "500", "clglob": ""}, {"lic": "9261952", "nom": "KILOULI", "prenom": "Ilyes", "points": "500", "clglob": ""}, {"lic": "9261951", "nom": "KILOULI", "prenom": "Nahil", "points": "500", "clglob": ""}, {"lic": "9261954", "nom": "LABIDI", "prenom": "Abdalaala", "points": "500", "clglob": ""}, {"lic": "9263884", "nom": "LACROIX", "prenom": "Solène", "points": "500", "clglob": ""}, {"lic": "9261955", "nom": "LAGRANGE", "prenom": "Enora", "points": "523", "clglob": ""}, {"lic": "9261956", "nom": "LASNE LARDILLIER", "prenom": "Tristan", "points": "500", "clglob": ""}, {"lic": "9261957", "nom": "LATAPIE", "prenom": "Charles", "points": "500", "clglob": ""}, {"lic": "9238823", "nom": "LAUFER", "prenom": "Marc", "points": "519", "clglob": ""}, {"lic": "9259500", "nom": "LAURENT PICQUE", "prenom": "Antonin", "points": "561", "clglob": ""}, {"lic": "9263871", "nom": "LE GOFF", "prenom": "Priam", "points": "500", "clglob": ""}, {"lic": "9238825", "nom": "LECONTE", "prenom": "Hugues", "points": "500", "clglob": ""}, {"lic": "9261959", "nom": "LECUYER", "prenom": "Haytem", "points": "500", "clglob": ""}, {"lic": "9266683", "nom": "LENOBLE JEANGEORGES", "prenom": "Paul", "points": "500", "clglob": ""}, {"lic": "9261960", "nom": "LEONARDI CUAZ", "prenom": "Alexis", "points": "500", "clglob": ""}, {"lic": "9266684", "nom": "LEROY TAILLE", "prenom": "Noah", "points": "500", "clglob": ""}, {"lic": "9263893", "nom": "LESELLIER", "prenom": "Tom", "points": "500", "clglob": ""}, {"lic": "9266685", "nom": "LEVY", "prenom": "Ava", "points": "500", "clglob": ""}, {"lic": "9266686", "nom": "LEVY", "prenom": "Nathan", "points": "500", "clglob": ""}, {"lic": "9266687", "nom": "LOMBARDO COLLOT", "prenom": "Florent", "points": "500", "clglob": ""}, {"lic": "9266688", "nom": "LOZANO", "prenom": "Raphaël", "points": "500", "clglob": ""}, {"lic": "9248490", "nom": "LULE", "prenom": "Sebastien", "points": "500", "clglob": ""}, {"lic": "9267811", "nom": "MARCQ", "prenom": "Quentin", "points": "500", "clglob": ""}, {"lic": "9263892", "nom": "MARCQ", "prenom": "Samuel", "points": "500", "clglob": ""}, {"lic": "9263886", "nom": "MERLET", "prenom": "Victor", "points": "500", "clglob": ""}, {"lic": "9266689", "nom": "MEYNIER", "prenom": "Alban", "points": "500", "clglob": ""}, {"lic": "9251833", "nom": "MICHEL", "prenom": "Georges", "points": "500", "clglob": ""}, {"lic": "9261015", "nom": "MIGNOT", "prenom": "Annick", "points": "500", "clglob": ""}, {"lic": "9261964", "nom": "MOLAWKA", "prenom": "Oliwier", "points": "500", "clglob": ""}, {"lic": "9247037", "nom": "MOREAU", "prenom": "Jean-Francois", "points": "500", "clglob": ""}, {"lic": "9251385", "nom": "MOSTAFAVI", "prenom": "Melissa", "points": "621", "clglob": ""}, {"lic": "9263906", "nom": "MULLIEZ", "prenom": "Alban", "points": "500", "clglob": ""}, {"lic": "9266672", "nom": "NIEMIEC", "prenom": "Szymon", "points": "500", "clglob": ""}, {"lic": "9259491", "nom": "NURDIANI", "prenom": "Galuh", "points": "500", "clglob": ""}, {"lic": "9236839", "nom": "OGIER", "prenom": "Gabriel", "points": "515", "clglob": ""}, {"lic": "7528937", "nom": "OH", "prenom": "Sook-Ja", "points": "500", "clglob": ""}, {"lic": "9263895", "nom": "OLLIVIER", "prenom": "Gaëtan", "points": "500", "clglob": ""}, {"lic": "9263909", "nom": "PASTRE", "prenom": "Marc", "points": "500", "clglob": ""}, {"lic": "9261967", "nom": "PATEYRON", "prenom": "Loup", "points": "500", "clglob": ""}, {"lic": "9263836", "nom": "PAVEE", "prenom": "Nelly", "points": "500", "clglob": ""}, {"lic": "9263910", "nom": "PELLE", "prenom": "Edgar", "points": "500", "clglob": ""}, {"lic": "9263911", "nom": "PELLETIER", "prenom": "Augustin", "points": "500", "clglob": ""}, {"lic": "9263835", "nom": "PENNETOT", "prenom": "Antoine", "points": "500", "clglob": ""}, {"lic": "9263885", "nom": "PETRESCO", "prenom": "Noé", "points": "500", "clglob": ""}, {"lic": "9263891", "nom": "PHILIPPE", "prenom": "Enzo", "points": "500", "clglob": ""}, {"lic": "9263888", "nom": "POPOT", "prenom": "Erwan", "points": "504", "clglob": ""}, {"lic": "9241001", "nom": "POTIER", "prenom": "Thomas", "points": "507", "clglob": ""}, {"lic": "9261440", "nom": "PRADERE", "prenom": "Ronan", "points": "500", "clglob": ""}, {"lic": "9263838", "nom": "RADIO", "prenom": "Gaelle", "points": "500", "clglob": ""}, {"lic": "9263877", "nom": "RAYNAUD PETRELLA", "prenom": "Emilie", "points": "500", "clglob": ""}, {"lic": "9266690", "nom": "REILHAC", "prenom": "Louis", "points": "500", "clglob": ""}, {"lic": "9266691", "nom": "REILHAC", "prenom": "Victoria", "points": "500", "clglob": ""}, {"lic": "9251840", "nom": "RIOU", "prenom": "Zadig", "points": "500", "clglob": ""}, {"lic": "9263872", "nom": "ROUSSET RECOURS", "prenom": "Lubin", "points": "500", "clglob": ""}, {"lic": "9249292", "nom": "ROUX", "prenom": "Amiel", "points": "602", "clglob": ""}, {"lic": "9263887", "nom": "ROUX LECLERCQ", "prenom": "Timothee", "points": "500", "clglob": ""}, {"lic": "9266692", "nom": "SADAT", "prenom": "Aksel", "points": "500", "clglob": ""}, {"lic": "9266607", "nom": "SAID ABDALLAH", "prenom": "Sofia", "points": "500", "clglob": ""}, {"lic": "9263873", "nom": "SALEM", "prenom": "Eva", "points": "500", "clglob": ""}, {"lic": "9261968", "nom": "SALEM", "prenom": "Noé", "points": "500", "clglob": ""}, {"lic": "9266693", "nom": "SALOMON", "prenom": "Clovis", "points": "500", "clglob": ""}, {"lic": "9251470", "nom": "SANCHEZ", "prenom": "Tom", "points": "500", "clglob": ""}, {"lic": "9263864", "nom": "SEGARD", "prenom": "Arthur", "points": "500", "clglob": ""}, {"lic": "9263698", "nom": "SERRE", "prenom": "Flavien", "points": "500", "clglob": ""}, {"lic": "9266694", "nom": "SICART-RIBEYROLLE", "prenom": "Antonio", "points": "500", "clglob": ""}, {"lic": "9261969", "nom": "STARK SAGNET", "prenom": "Julien", "points": "500", "clglob": ""}, {"lic": "9264099", "nom": "TADEVOSYAN", "prenom": "Tigran", "points": "500", "clglob": ""}, {"lic": "9263858", "nom": "TAMBURLINI", "prenom": "Arthur", "points": "500", "clglob": ""}, {"lic": "9263899", "nom": "THERY", "prenom": "Augustin", "points": "500", "clglob": ""}, {"lic": "9267418", "nom": "THIOUNE", "prenom": "Abdoul Aziz", "points": "500", "clglob": ""}, {"lic": "9257461", "nom": "TORRES DE SOUSA", "prenom": "Vittorio", "points": "563", "clglob": ""}, {"lic": "9263907", "nom": "TRAN", "prenom": "Hanaé", "points": "500", "clglob": ""}, {"lic": "7872346", "nom": "TRUGUET", "prenom": "Patrick", "points": "500", "clglob": ""}, {"lic": "9261971", "nom": "VACHER", "prenom": "Anatole", "points": "500", "clglob": ""}, {"lic": "9263879", "nom": "VAN WEYDEVELT", "prenom": "Victor", "points": "500", "clglob": ""}, {"lic": "759547", "nom": "VINANT", "prenom": "Pierre", "points": "763", "clglob": ""}, {"lic": "9266695", "nom": "VINCENT", "prenom": "Amaury", "points": "500", "clglob": ""}, {"lic": "9266696", "nom": "VINCENT", "prenom": "Gauthier", "points": "500", "clglob": ""}, {"lic": "9257427", "nom": "VINCENT", "prenom": "Noa", "points": "500", "clglob": ""}, {"lic": "9251847", "nom": "VINCENT", "prenom": "Robin", "points": "645", "clglob": ""}, {"lic": "9266697", "nom": "VINCENT", "prenom": "Sacha", "points": "500", "clglob": ""}, {"lic": "9266698", "nom": "WANG", "prenom": "Hanna", "points": "500", "clglob": ""}, {"lic": "9257463", "nom": "WURTZ ABOAB", "prenom": "Joachim", "points": "504", "clglob": ""}, {"lic": "9257441", "nom": "YANG", "prenom": "Axel", "points": "1040", "clglob": ""}, {"lic": "9259498", "nom": "YANG", "prenom": "Eloy", "points": "500", "clglob": ""}, {"lic": "9257442", "nom": "YANG", "prenom": "Izac", "points": "736", "clglob": ""}, {"lic": "9263837", "nom": "YATIM", "prenom": "Joseph", "points": "500", "clglob": ""}, {"lic": "9261972", "nom": "YATIM", "prenom": "Paul", "points": "500", "clglob": ""}, {"lic": "9263874", "nom": "YOULOU BITSINDOU", "prenom": "Ethan", "points": "500", "clglob": ""}, {"lic": "9261973", "nom": "ZARKANDI", "prenom": "Armaan", "points": "500", "clglob": ""}, {"lic": "9261974", "nom": "ZARKANDI", "prenom": "Nolan", "points": "500", "clglob": ""}, {"lic": "9266699", "nom": "ZHU", "prenom": "Sylvain", "points": "500", "clglob": ""}]}