{"club": "DASSAULT SPORTS", "numero": "08921522", "joueurs": [{"lic": "7830611", "nom": "AIT AKKOUCHE", "prenom": "Pierre", "points": "517", "clglob": ""}, {"lic": "759120", "nom": "CHASTANG", "prenom": "Cedric", "points": "923", "clglob": ""}, {"lic": "9264283", "nom": "GARNIER", "prenom": "Eric", "points": "500", "clglob": ""}, {"lic": "4434244", "nom": "LEFEUVRE", "prenom": "Jerome", "points": "668", "clglob": ""}, {"lic": "9252708", "nom": "MARCUZZI", "prenom": "Marie-Francoise", "points": "500", "clglob": ""}, {"lic": "9264606", "nom": "PHAN", "prenom": "Katia", "points": "500", "clglob": ""}, {"lic": "9251610", "nom": "RAST", "prenom": "Jean-Paul", "points": "500", "clglob": ""}, {"lic": "2929220", "nom": "SALESSE", "prenom": "Laurent", "points": "858", "clglob": ""}]}