{"division": "L08_R3 Messieurs phase 1 Poule 1", "organisme": "16", "phase": "1", "poule": 16, "cx_poule": 1142347, "classement": [{"clt": "1", "equipe": "BONDOUFLE DUCKS 3", "pts": "21", "joue": "7", "vic": "7", "nul": "0", "def": "0", "pg": "174", "pp": "116"}, {"clt": "2", "equipe": "PUTEAUX TT CSM 1", "pts": "19", "joue": "7", "vic": "6", "nul": "0", "def": "1", "pg": "164", "pp": "122"}, {"clt": "3", "equipe": "VILLECRESNES ALTT 2", "pts": "17", "joue": "7", "vic": "5", "nul": "0", "def": "2", "pg": "165", "pp": "129"}, {"clt": "4", "equipe": "LEVALLOIS SPORT 7", "pts": "15", "joue": "7", "vic": "4", "nul": "0", "def": "3", "pg": "144", "pp": "150"}, {"clt": "5", "equipe": "COURBEVOIE STT 6", "pts": "13", "joue": "7", "vic": "3", "nul": "0", "def": "4", "pg": "150", "pp": "144"}, {"clt": "6", "equipe": "SAINT REMY TT 1", "pts": "11", "joue": "7", "vic": "2", "nul": "0", "def": "5", "pg": "135", "pp": "155"}, {"clt": "7", "equipe": "PARIS SP20 TT 6", "pts": "9", "joue": "7", "vic": "1", "nul": "0", "def": "6", "pg": "125", "pp": "161"}, {"clt": "8", "equipe": "MERY 2", "pts": "7", "joue": "7", "vic": "0", "nul": "0", "def": "7", "pg": "99", "pp": "179"}], "rencontres": [{"date": "20/09/2025", "equa": "SAINT REMY TT 1", "equb": "PUTEAUX TT CSM 1", "scorea": "18", "scoreb": "24", "compo_a": [{"nom": "CAUSSE Philippe", "pts": 1704}, {"nom": "BROCHE David", "pts": 1416}, {"nom": "RAYNAUD Nicolas", "pts": 1516}, {"nom": "DIJOUX Pascal", "pts": 1545}], "compo_b": [{"nom": "THIERY Didier", "pts": 1545}, {"nom": "ROFFI Jean Michel", "pts": 1369}, {"nom": "GARCIA Ludovic", "pts": 1497}, {"nom": "ANTOINE Matthieu", "pts": 1121}]}, {"date": "20/09/2025", "equa": "VILLECRESNES ALTT 2", "equb": "COURBEVOIE STT 6", "scorea": "25", "scoreb": "17", "compo_a": [{"nom": "SAROTTE Thomas", "pts": 1719}, {"nom": "KONATE Mohamed", "pts": 1613}, {"nom": "ALLUIN-DELACOUR Killian", "pts": 1696}, {"nom": "SYLVESTRE Ludovic", "pts": 1310}], "compo_b": [{"nom": "MARCOS Ruben", "pts": 1360}, {"nom": "RAHUL DON RUDY Haresh Singh", "pts": 1437}, {"nom": "GODART Kevin", "pts": 1417}, {"nom": "PINO David", "pts": 1368}]}, {"date": "20/09/2025", "equa": "LEVALLOIS SPORT 7", "equb": "MERY 2", "scorea": "23", "scoreb": "19", "compo_a": [{"nom": "RAELISON Nikk", "pts": 1548}, {"nom": "PAUMARD Mathieu", "pts": 1609}, {"nom": "PULCI Manuel", "pts": 1417}, {"nom": "STEIN Thomas", "pts": 1371}], "compo_b": [{"nom": "HACHARD Ilan", "pts": 1754}, {"nom": "LE SAGE Vincent", "pts": 1326}, {"nom": "LEMIRE Quentin", "pts": 1417}, {"nom": "GUTH Boris", "pts": 1252}]}, {"date": "20/09/2025", "equa": "BONDOUFLE DUCKS 3", "equb": "PARIS SP20 TT 6", "scorea": "26", "scoreb": "16", "compo_a": [{"nom": "PERES Julien", "pts": 1547}, {"nom": "ALIF Gilles", "pts": 1678}, {"nom": "ERARD Stephane", "pts": 1858}, {"nom": "BOURDONNEAU Tanguy", "pts": 1671}], "compo_b": [{"nom": "BOUSQUET Pierre", "pts": 1329}, {"nom": "CORDIER-MONTOURCY Alexis", "pts": 1154}, {"nom": "BEDORET Gabriel", "pts": 1237}, {"nom": "SUCULLULU Veli", "pts": 1139}]}, {"date": "04/10/2025", "equa": "COURBEVOIE STT 6", "equb": "SAINT REMY TT 1", "scorea": "27", "scoreb": "15", "compo_a": [{"nom": "GARCIA Ludovic", "pts": 1497}, {"nom": "GINESTE Mathieu", "pts": 1299}, {"nom": "VILLEROY Marc", "pts": 872}, {"nom": "ROFFI Jean Michel", "pts": 1369}], "compo_b": [{"nom": "DE GREEF Francois", "pts": 1722}, {"nom": "MARCOS Ruben", "pts": 1360}, {"nom": "GREVET Adrien", "pts": 1663}, {"nom": "RAHUL DON RUDY Haresh Singh", "pts": 1437}]}, {"date": "04/10/2025", "equa": "MERY 2", "equb": "VILLECRESNES ALTT 2", "scorea": "16", "scoreb": "26", "compo_a": [{"nom": "LEMIRE Quentin", "pts": 1417}, {"nom": "BRAVO Bernard", "pts": 702}, {"nom": "LE SAGE Vincent", "pts": 1326}, {"nom": "GUTH Boris", "pts": 1252}], "compo_b": [{"nom": "KONATE Mohamed", "pts": 1613}, {"nom": "SAROTTE Thomas", "pts": 1719}, {"nom": "ALLUIN-DELACOUR Killian", "pts": 1696}, {"nom": "SYLVESTRE Ludovic", "pts": 1310}]}, {"date": "04/10/2025", "equa": "PARIS SP20 TT 6", "equb": "LEVALLOIS SPORT 7", "scorea": "20", "scoreb": "22", "compo_a": [{"nom": "INTINS David", "pts": 1679}, {"nom": "PETIBON Emmanuel", "pts": 1383}, {"nom": "STEIN Thomas", "pts": 1371}, {"nom": "COHEN MELKA Nathan", "pts": 1261}], "compo_b": [{"nom": "CORDIER-MONTOURCY Alexis", "pts": 1154}, {"nom": "GODARD Maxime", "pts": 1198}, {"nom": "VOJINOVITCH Romain", "pts": 1319}, {"nom": "BOUSQUET Pierre", "pts": 1329}]}, {"date": "04/10/2025", "equa": "PUTEAUX TT CSM 1", "equb": "BONDOUFLE DUCKS 3", "scorea": "19", "scoreb": "23", "compo_a": [{"nom": "ALIF Gilles", "pts": 1678}, {"nom": "FOURNIAL Jerome", "pts": 1516}, {"nom": "PERES Julien", "pts": 1547}, {"nom": "LHULLIER Thomas", "pts": 1570}], "compo_b": [{"nom": "CAUSSE Philippe", "pts": 1704}, {"nom": "BROCHE David", "pts": 1416}, {"nom": "RAYNAUD Nicolas", "pts": 1516}, {"nom": "DIJOUX Pascal", "pts": 1545}]}, {"date": "11/10/2025", "equa": "SAINT REMY TT 1", "equb": "MERY 2", "scorea": "25", "scoreb": "13", "compo_a": [{"nom": "SOUNIE Mathieu", "pts": 1570}, {"nom": "GARCIA Ludovic", "pts": 1497}, {"nom": "ROFFI Jean Michel", "pts": 1369}, {"nom": "MERCIER William", "pts": 699}], "compo_b": [{"nom": "LE SAGE Vincent", "pts": 1326}, {"nom": "MIELLE Cedric", "pts": 726}, {"nom": "GUTH Boris", "pts": 1252}]}, {"date": "11/10/2025", "equa": "VILLECRESNES ALTT 2", "equb": "PARIS SP20 TT 6", "scorea": "25", "scoreb": "17", "compo_a": [{"nom": "VOJINOVITCH Romain", "pts": 1319}, {"nom": "GODARD Maxime", "pts": 1198}, {"nom": "CORDIER-MONTOURCY Alexis", "pts": 1154}, {"nom": "BEDORET Gabriel", "pts": 1237}], "compo_b": [{"nom": "BELAID Nabil", "pts": 1232}, {"nom": "ALLUIN-DELACOUR Killian", "pts": 1696}, {"nom": "SAROTTE Thomas", "pts": 1719}, {"nom": "SYLVESTRE Ludovic", "pts": 1310}]}, {"date": "11/10/2025", "equa": "LEVALLOIS SPORT 7", "equb": "BONDOUFLE DUCKS 3", "scorea": "19", "scoreb": "23", "compo_a": [{"nom": "BOUVAIS Thomas", "pts": 1981}, {"nom": "LE METTER Theophile", "pts": 1728}, {"nom": "STEIN Thomas", "pts": 1371}, {"nom": "SELETZKY Marc-David", "pts": 1596}], "compo_b": [{"nom": "BOURDONNEAU Tanguy", "pts": 1671}, {"nom": "PERES Julien", "pts": 1547}, {"nom": "ERARD Stephane", "pts": 1858}, {"nom": "LHULLIER Thomas", "pts": 1570}]}, {"date": "11/10/2025", "equa": "PUTEAUX TT CSM 1", "equb": "COURBEVOIE STT 6", "scorea": "24", "scoreb": "18", "compo_a": [{"nom": "RAHUL DON RUDY Haresh Singh", "pts": 1437}, {"nom": "MARCOS Ruben", "pts": 1360}, {"nom": "GODART Kevin", "pts": 1417}, {"nom": "PINO David", "pts": 1368}], "compo_b": [{"nom": "CAUSSE Philippe", "pts": 1704}, {"nom": "BROCHE David", "pts": 1416}, {"nom": "RAYNAUD Nicolas", "pts": 1516}, {"nom": "DIJOUX Pascal", "pts": 1545}]}, {"date": "15/11/2025", "equa": "PARIS SP20 TT 6", "equb": "SAINT REMY TT 1", "scorea": "19", "scoreb": "23", "compo_a": [{"nom": "BOUSQUET Pierre", "pts": 1329}, {"nom": "BEDORET Gabriel", "pts": 1237}, {"nom": "BARRE Victor", "pts": 1280}, {"nom": "PAUTY Eliott", "pts": 964}], "compo_b": [{"nom": "DURAND Thomas", "pts": 1599}, {"nom": "GARCIA Ludovic", "pts": 1497}, {"nom": "TERRADE Alexandre", "pts": 1538}, {"nom": "ROFFI Jean Michel", "pts": 1369}]}, {"date": "15/11/2025", "equa": "BONDOUFLE DUCKS 3", "equb": "VILLECRESNES ALTT 2", "scorea": "23", "scoreb": "19", "compo_a": [{"nom": "BOURDONNEAU Tanguy", "pts": 1671}, {"nom": "ALIF Gilles", "pts": 1678}, {"nom": "ERARD Stephane", "pts": 1858}, {"nom": "LHULLIER Thomas", "pts": 1570}], "compo_b": [{"nom": "SAROTTE Thomas", "pts": 1719}, {"nom": "KONATE Mohamed", "pts": 1613}, {"nom": "ALLUIN-DELACOUR Killian", "pts": 1696}, {"nom": "SYLVESTRE Ludovic", "pts": 1310}]}, {"date": "15/11/2025", "equa": "LEVALLOIS SPORT 7", "equb": "PUTEAUX TT CSM 1", "scorea": "20", "scoreb": "22", "compo_a": [{"nom": "LE METTER Theophile", "pts": 1728}, {"nom": "INTINS David", "pts": 1679}, {"nom": "STEIN Thomas", "pts": 1371}, {"nom": "REDON Thierry", "pts": 1966}], "compo_b": [{"nom": "CAUSSE Philippe", "pts": 1704}, {"nom": "DIJOUX Pascal", "pts": 1545}, {"nom": "RAYNAUD Nicolas", "pts": 1516}, {"nom": "BROCHE David", "pts": 1416}]}, {"date": "15/11/2025", "equa": "MERY 2", "equb": "COURBEVOIE STT 6", "scorea": "19", "scoreb": "23", "compo_a": [{"nom": "LE SAGE Vincent", "pts": 1326}, {"nom": "BERLAND Romain", "pts": 1697}, {"nom": "VARNICA Sacha", "pts": 1569}, {"nom": "GUTH Boris", "pts": 1252}], "compo_b": [{"nom": "GREVET Adrien", "pts": 1663}, {"nom": "MARCOS Ruben", "pts": 1360}, {"nom": "RAHUL DON RUDY Haresh Singh", "pts": 1437}, {"nom": "PINO David", "pts": 1368}]}, {"date": "29/11/2025", "equa": "SAINT REMY TT 1", "equb": "BONDOUFLE DUCKS 3", "scorea": "16", "scoreb": "26", "compo_a": [{"nom": "ROFFI Jean Michel", "pts": 1369}, {"nom": "GUILLORY Cyprien", "pts": 584}, {"nom": "GARCIA Ludovic", "pts": 1497}, {"nom": "FROIDUROT Bernard", "pts": 1030}], "compo_b": [{"nom": "LHULLIER Thomas", "pts": 1570}, {"nom": "ALIF Gilles", "pts": 1678}, {"nom": "PERES Julien", "pts": 1547}, {"nom": "FOURNIAL Jerome", "pts": 1516}]}, {"date": "29/11/2025", "equa": "VILLECRESNES ALTT 2", "equb": "LEVALLOIS SPORT 7", "scorea": "28", "scoreb": "14", "compo_a": [{"nom": "PULCI Manuel", "pts": 1417}, {"nom": "PETIBON Emmanuel", "pts": 1383}, {"nom": "STEIN Thomas", "pts": 1371}, {"nom": "PLUYAUD Nicolas", "pts": 906}], "compo_b": [{"nom": "SAROTTE Thomas", "pts": 1719}, {"nom": "SYLVESTRE Ludovic", "pts": 1310}, {"nom": "KONATE Mohamed", "pts": 1613}, {"nom": "ALLUIN-DELACOUR Killian", "pts": 1696}]}, {"date": "29/11/2025", "equa": "COURBEVOIE STT 6", "equb": "PARIS SP20 TT 6", "scorea": "28", "scoreb": "14", "compo_a": [{"nom": "GREVET Adrien", "pts": 1663}, {"nom": "MARCOS Ruben", "pts": 1360}, {"nom": "RAHUL DON RUDY Haresh Singh", "pts": 1437}, {"nom": "PINO David", "pts": 1368}], "compo_b": [{"nom": "VOJINOVITCH Romain", "pts": 1319}, {"nom": "BOUFFIER Joachim", "pts": 1111}, {"nom": "DE GOURNAY Christophe", "pts": 1123}, {"nom": "CORDIER-MONTOURCY Alexis", "pts": 1154}]}, {"date": "29/11/2025", "equa": "PUTEAUX TT CSM 1", "equb": "MERY 2", "scorea": "27", "scoreb": "11", "compo_a": [{"nom": "LE SAGE Vincent", "pts": 1326}, {"nom": "JOUANNET Sophie", "pts": 801}, {"nom": "GUTH Boris", "pts": 1252}], "compo_b": [{"nom": "BROCHE David", "pts": 1416}, {"nom": "CAUSSE Philippe", "pts": 1704}, {"nom": "DIJOUX Pascal", "pts": 1545}, {"nom": "RAYNAUD Nicolas", "pts": 1516}]}, {"date": "13/12/2025", "equa": "LEVALLOIS SPORT 7", "equb": "SAINT REMY TT 1", "scorea": "24", "scoreb": "18", "compo_a": [{"nom": "LE METTER Theophile", "pts": 1728}, {"nom": "PETIBON Emmanuel", "pts": 1383}, {"nom": "PULCI Manuel", "pts": 1417}, {"nom": "STEIN Thomas", "pts": 1371}], "compo_b": [{"nom": "ROFFI Jean Michel", "pts": 1369}, {"nom": "TRICHON Timothee", "pts": 537}, {"nom": "GARCIA Ludovic", "pts": 1497}, {"nom": "SMADJA Philippe", "pts": 699}]}, {"date": "13/12/2025", "equa": "VILLECRESNES ALTT 2", "equb": "PUTEAUX TT CSM 1", "scorea": "20", "scoreb": "22", "compo_a": [{"nom": "CAUSSE Philippe", "pts": 1704}, {"nom": "DIJOUX Pascal", "pts": 1545}, {"nom": "RAYNAUD Nicolas", "pts": 1516}, {"nom": "BROCHE David", "pts": 1416}], "compo_b": [{"nom": "KONATE Mohamed", "pts": 1613}, {"nom": "SAROTTE Thomas", "pts": 1719}, {"nom": "BLANC Leny", "pts": 1174}, {"nom": "SYLVESTRE Ludovic", "pts": 1310}]}, {"date": "13/12/2025", "equa": "BONDOUFLE DUCKS 3", "equb": "COURBEVOIE STT 6", "scorea": "25", "scoreb": "17", "compo_a": [{"nom": "PINO David", "pts": 1368}, {"nom": "MARCOS Ruben", "pts": 1360}, {"nom": "RAHUL DON RUDY Haresh Singh", "pts": 1437}, {"nom": "MARCOS Nicolas", "pts": 577}], "compo_b": [{"nom": "PERES Julien", "pts": 1547}, {"nom": "FOURNIAL Jerome", "pts": 1516}, {"nom": "ALIF Gilles", "pts": 1678}, {"nom": "LHULLIER Thomas", "pts": 1570}]}, {"date": "13/12/2025", "equa": "PARIS SP20 TT 6", "equb": "MERY 2", "scorea": "27", "scoreb": "11", "compo_a": [{"nom": "GODARD Maxime", "pts": 1198}, {"nom": "VOJINOVITCH Romain", "pts": 1319}, {"nom": "BOUSQUET Pierre", "pts": 1329}, {"nom": "BEDORET Gabriel", "pts": 1237}], "compo_b": [{"nom": "PANISSIER Quentin", "pts": 719}, {"nom": "PERRIN Gabriel", "pts": 978}, {"nom": "GUTH Boris", "pts": 1252}]}, {"date": "10/01/2026", "equa": "SAINT REMY TT 1", "equb": "VILLECRESNES ALTT 2", "scorea": "20", "scoreb": "22", "compo_a": [{"nom": "ROFFI Jean Michel", "pts": 1369}, {"nom": "GARCIA Ludovic", "pts": 1497}, {"nom": "CAZERES Frederic", "pts": 665}, {"nom": "DURAND Thomas", "pts": 1599}], "compo_b": [{"nom": "ALLUIN-DELACOUR Killian", "pts": 1696}, {"nom": "KONATE Mohamed", "pts": 1613}, {"nom": "MATEOS Christophe", "pts": 1213}, {"nom": "REYNOLDS Gregory", "pts": 1189}]}, {"date": "10/01/2026", "equa": "COURBEVOIE STT 6", "equb": "LEVALLOIS SPORT 7", "scorea": "20", "scoreb": "22", "compo_a": [{"nom": "GODART Kevin", "pts": 1417}, {"nom": "RAHUL DON RUDY Haresh Singh", "pts": 1437}, {"nom": "PINO David", "pts": 1368}, {"nom": "TREFEIL Keylian", "pts": 1256}], "compo_b": [{"nom": "PETIBON Emmanuel", "pts": 1383}, {"nom": "CAI Victor", "pts": 898}, {"nom": "STEIN Thomas", "pts": 1371}, {"nom": "CUSTOS Xavier", "pts": 1353}]}, {"date": "10/01/2026", "equa": "MERY 2", "equb": "BONDOUFLE DUCKS 3", "scorea": "10", "scoreb": "28", "compo_a": [{"nom": "PERRIN Gabriel", "pts": 978}, {"nom": "PANISSIER Quentin", "pts": 719}, {"nom": "GUTH Boris", "pts": 1252}], "compo_b": [{"nom": "ALIF Gilles", "pts": 1678}, {"nom": "PERES Julien", "pts": 1547}, {"nom": "LHULLIER Thomas", "pts": 1570}, {"nom": "FOURNIAL Jerome", "pts": 1516}]}, {"date": "10/01/2026", "equa": "PUTEAUX TT CSM 1", "equb": "PARIS SP20 TT 6", "scorea": "26", "scoreb": "12", "compo_a": [{"nom": "VOJINOVITCH Romain", "pts": 1319}, {"nom": "BEDORET Gabriel", "pts": 1237}, {"nom": "BOUSQUET Pierre", "pts": 1329}, {"nom": "DE GOURNAY Christophe", "pts": 1123}], "compo_b": [{"nom": "BROCHE David", "pts": 1416}, {"nom": "JOLY Vincent", "pts": 1132}, {"nom": "RAYNAUD Nicolas", "pts": 1516}, {"nom": "SEYER Guillaume", "pts": 1045}]}]}