{"division": "L08_R3 Messieurs phase 1 Poule 1", "organisme": "16", "phase": "1", "poule": 7, "cx_poule": 1142338, "classement": [{"clt": "1", "equipe": "ANTONY SPORT TT 3", "pts": "21", "joue": "7", "vic": "7", "nul": "0", "def": "0", "pg": "169", "pp": "125"}, {"clt": "2", "equipe": "NOISY LE GRAND 6", "pts": "17", "joue": "7", "vic": "5", "nul": "0", "def": "2", "pg": "156", "pp": "136"}, {"clt": "3", "equipe": "ROSNY JA 1", "pts": "16", "joue": "7", "vic": "4", "nul": "1", "def": "2", "pg": "156", "pp": "138"}, {"clt": "4", "equipe": "ORMESSON US 1", "pts": "15", "joue": "7", "vic": "4", "nul": "0", "def": "3", "pg": "145", "pp": "147"}, {"clt": "5", "equipe": "JUMP 5", "pts": "14", "joue": "7", "vic": "3", "nul": "1", "def": "3", "pg": "143", "pp": "150"}, {"clt": "6", "equipe": "SAINT MAUR VGA US 3", "pts": "13", "joue": "7", "vic": "3", "nul": "0", "def": "4", "pg": "147", "pp": "147"}, {"clt": "7", "equipe": "SQY PING 5", "pts": "8", "joue": "7", "vic": "0", "nul": "1", "def": "6", "pg": "137", "pp": "156"}, {"clt": "8", "equipe": "ESP REUILLY 4", "pts": "8", "joue": "7", "vic": "0", "nul": "1", "def": "6", "pg": "120", "pp": "174"}], "rencontres": [{"date": "20/09/2025", "equa": "ESP REUILLY 4", "equb": "JUMP 5", "scorea": "19", "scoreb": "23", "compo_a": [{"nom": "GORAL Raphael", "pts": 1302}, {"nom": "SCHOTT Nicolas", "pts": 1228}, {"nom": "CHEMOUL Jeremie", "pts": 1273}, {"nom": "LOPEZ Victor", "pts": 1315}], "compo_b": [{"nom": "YANG Junfu", "pts": 1417}, {"nom": "DAHERON Martin", "pts": 1371}, {"nom": "NIKOLIC Daniel", "pts": 1488}, {"nom": "BOUDENNE Aurélien", "pts": 1438}]}, {"date": "20/09/2025", "equa": "ORMESSON US 1", "equb": "NOISY LE GRAND 6", "scorea": "15", "scoreb": "25", "compo_a": [{"nom": "DASSÉ Florian", "pts": 1324}, {"nom": "HOFFMANN-DRIF Tom", "pts": 1434}, {"nom": "VARONA Quentin", "pts": 1477}, {"nom": "CAPDELLAYRE Gary", "pts": 1724}], "compo_b": [{"nom": "MEGUIRA Ruben", "pts": 1464}, {"nom": "MONCANY Jeremy", "pts": 1448}, {"nom": "TCHAKHOTINE Guillaume", "pts": 1637}, {"nom": "LUIS Théo", "pts": 1418}]}, {"date": "20/09/2025", "equa": "SAINT MAUR VGA US 3", "equb": "SQY PING 5", "scorea": "22", "scoreb": "20", "compo_a": [{"nom": "NGUYEN TAKIZAWA Taiga", "pts": 1287}, {"nom": "YVONNET Nathan", "pts": 1342}, {"nom": "FAVREAU Célian", "pts": 1144}, {"nom": "DESVAQUET Hippolyte", "pts": 1335}], "compo_b": [{"nom": "MERLINI Pascal", "pts": 1361}, {"nom": "BOUCHENDHOMME Alexandre", "pts": 1217}, {"nom": "SALMON Olivier", "pts": 1229}, {"nom": "MICHET HUET Gabriel", "pts": 1186}]}, {"date": "20/09/2025", "equa": "ROSNY JA 1", "equb": "ANTONY SPORT TT 3", "scorea": "18", "scoreb": "24", "compo_a": [{"nom": "COEURET Guillaume", "pts": 1584}, {"nom": "BARJON Etienne", "pts": 1632}, {"nom": "NOIRET Stephane", "pts": 1212}, {"nom": "ROUSSILLON Noe", "pts": 1001}], "compo_b": [{"nom": "ROUSSEL Thibault", "pts": 1483}, {"nom": "ZHANG Theo", "pts": 1465}, {"nom": "MAYOMBO Tommy", "pts": 1624}, {"nom": "ION Alexandru", "pts": 1466}]}, {"date": "04/10/2025", "equa": "NOISY LE GRAND 6", "equb": "ESP REUILLY 4", "scorea": "27", "scoreb": "15", "compo_a": [{"nom": "MEGUIRA Ruben", "pts": 1464}, {"nom": "LISENA Mathis", "pts": 1434}, {"nom": "TCHAKHOTINE Guillaume", "pts": 1637}, {"nom": "MONCANY Jeremy", "pts": 1448}], "compo_b": [{"nom": "LORMANT Stephane", "pts": 1304}, {"nom": "GUEDES Emmanuel", "pts": 1188}, {"nom": "GORAL Raphael", "pts": 1302}, {"nom": "LOPEZ Victor", "pts": 1315}]}, {"date": "04/10/2025", "equa": "SQY PING 5", "equb": "ORMESSON US 1", "scorea": "20", "scoreb": "22", "compo_a": [{"nom": "MERLINI Pascal", "pts": 1361}, {"nom": "SUAREZ Aurelien", "pts": 1318}, {"nom": "BOUSSAA Aylan", "pts": 1140}, {"nom": "BOUCHENDHOMME Alexandre", "pts": 1217}], "compo_b": [{"nom": "HURE Sebastien", "pts": 1818}, {"nom": "DASSÉ Florian", "pts": 1324}, {"nom": "DE ALMEIDA Terence", "pts": 917}, {"nom": "HOFFMANN-DRIF Tom", "pts": 1434}]}, {"date": "04/10/2025", "equa": "ANTONY SPORT TT 3", "equb": "SAINT MAUR VGA US 3", "scorea": "24", "scoreb": "18", "compo_a": [{"nom": "ZHANG Theo", "pts": 1465}, {"nom": "ROUSSEL Thibault", "pts": 1483}, {"nom": "ION Alexandru", "pts": 1466}, {"nom": "VIALLES Jean Michel", "pts": 1257}], "compo_b": [{"nom": "DELANNES Alexis", "pts": 1315}, {"nom": "YVONNET Nathan", "pts": 1342}, {"nom": "DESVAQUET Hippolyte", "pts": 1335}, {"nom": "LECUYER Ines", "pts": 1222}]}, {"date": "04/10/2025", "equa": "JUMP 5", "equb": "ROSNY JA 1", "scorea": "21", "scoreb": "21", "compo_a": [{"nom": "BOUDENNE Aurélien", "pts": 1438}, {"nom": "JOW Christophe", "pts": 1366}, {"nom": "LEFEBURE Julien", "pts": 1239}, {"nom": "YANG Junfu", "pts": 1417}], "compo_b": [{"nom": "BARJON Etienne", "pts": 1632}, {"nom": "TOUBOUL Olivier", "pts": 1042}, {"nom": "COEURET Guillaume", "pts": 1584}, {"nom": "FOVIAUX Luc", "pts": 1226}]}, {"date": "11/10/2025", "equa": "ESP REUILLY 4", "equb": "SQY PING 5", "scorea": "21", "scoreb": "21", "compo_a": [{"nom": "SCHOTT Nicolas", "pts": 1228}, {"nom": "LOPEZ Victor", "pts": 1315}, {"nom": "GUEDES Emmanuel", "pts": 1188}, {"nom": "CHEMOUL Jeremie", "pts": 1273}], "compo_b": [{"nom": "SUAREZ Aurelien", "pts": 1318}, {"nom": "MERLINI Pascal", "pts": 1361}, {"nom": "QUOIREZ Alexandre", "pts": 1432}, {"nom": "BOUCHENDHOMME Alexandre", "pts": 1217}]}, {"date": "11/10/2025", "equa": "ORMESSON US 1", "equb": "ANTONY SPORT TT 3", "scorea": "17", "scoreb": "25", "compo_a": [{"nom": "CAPDELLAYRE Gary", "pts": 1724}, {"nom": "DASSÉ Florian", "pts": 1324}, {"nom": "CARREIRA Philippe", "pts": 1148}, {"nom": "HOFFMANN-DRIF Tom", "pts": 1434}], "compo_b": [{"nom": "MAYOMBO Tommy", "pts": 1624}, {"nom": "ION Alexandru", "pts": 1466}, {"nom": "ZHANG Theo", "pts": 1465}, {"nom": "ROUSSEL Thibault", "pts": 1483}]}, {"date": "11/10/2025", "equa": "SAINT MAUR VGA US 3", "equb": "ROSNY JA 1", "scorea": "19", "scoreb": "23", "compo_a": [{"nom": "DELANNES Alexis", "pts": 1315}, {"nom": "YVONNET Nathan", "pts": 1342}, {"nom": "GENIN Nicolas", "pts": 1457}, {"nom": "DESVAQUET Hippolyte", "pts": 1335}], "compo_b": [{"nom": "BARJON Etienne", "pts": 1632}, {"nom": "AUTHIA Julien", "pts": 1786}, {"nom": "COEURET Guillaume", "pts": 1584}, {"nom": "IMAQUE Stephane", "pts": 1281}]}, {"date": "11/10/2025", "equa": "JUMP 5", "equb": "NOISY LE GRAND 6", "scorea": "19", "scoreb": "23", "compo_a": [{"nom": "BOUDENNE Aurélien", "pts": 1438}, {"nom": "YANG Junfu", "pts": 1417}, {"nom": "DAHERON Martin", "pts": 1371}, {"nom": "MOCQUAIS Olivier", "pts": 1428}], "compo_b": [{"nom": "MEGUIRA Ruben", "pts": 1464}, {"nom": "LISENA Mathis", "pts": 1434}, {"nom": "TCHAKHOTINE Guillaume", "pts": 1637}, {"nom": "LUIS Théo", "pts": 1418}]}, {"date": "15/11/2025", "equa": "ANTONY SPORT TT 3", "equb": "ESP REUILLY 4", "scorea": "25", "scoreb": "17", "compo_a": [{"nom": "MAYOMBO Tommy", "pts": 1624}, {"nom": "ROUSSEL Thibault", "pts": 1483}, {"nom": "ION Alexandru", "pts": 1466}, {"nom": "ZHANG Theo", "pts": 1465}], "compo_b": [{"nom": "LOPEZ Victor", "pts": 1315}, {"nom": "SCHOTT Nicolas", "pts": 1228}, {"nom": "HUYNH BACH SAC Tom", "pts": 938}, {"nom": "CHEMOUL Jeremie", "pts": 1273}]}, {"date": "15/11/2025", "equa": "ROSNY JA 1", "equb": "ORMESSON US 1", "scorea": "19", "scoreb": "23", "compo_a": [{"nom": "HURE Sebastien", "pts": 1818}, {"nom": "DASSÉ Florian", "pts": 1324}, {"nom": "HOFFMANN-DRIF Tom", "pts": 1434}, {"nom": "CAPDELLAYRE Gary", "pts": 1724}], "compo_b": [{"nom": "JOURDREN Remi", "pts": 1762}, {"nom": "BARJON Etienne", "pts": 1632}, {"nom": "COEURET Guillaume", "pts": 1584}, {"nom": "FOVIAUX Luc", "pts": 1226}]}, {"date": "15/11/2025", "equa": "SAINT MAUR VGA US 3", "equb": "JUMP 5", "scorea": "20", "scoreb": "22", "compo_a": [{"nom": "YVONNET Nathan", "pts": 1342}, {"nom": "BOUGEARD Matthieu", "pts": 1139}, {"nom": "DESVAQUET Hippolyte", "pts": 1335}, {"nom": "GENIN Nicolas", "pts": 1457}], "compo_b": [{"nom": "MOCQUAIS Olivier", "pts": 1428}, {"nom": "CHAN Mickael", "pts": 1437}, {"nom": "JOW Christophe", "pts": 1366}, {"nom": "YANG Junfu", "pts": 1417}]}, {"date": "15/11/2025", "equa": "SQY PING 5", "equb": "NOISY LE GRAND 6", "scorea": "19", "scoreb": "23", "compo_a": [{"nom": "MERLINI Pascal", "pts": 1361}, {"nom": "SUAREZ Aurelien", "pts": 1318}, {"nom": "GOSSA Baptiste", "pts": 1168}, {"nom": "BOUCHENDHOMME Alexandre", "pts": 1217}], "compo_b": [{"nom": "LISENA Mathis", "pts": 1434}, {"nom": "MONCANY Jeremy", "pts": 1448}, {"nom": "ZURITA Ennio", "pts": 1383}, {"nom": "LUIS Théo", "pts": 1418}]}, {"date": "29/11/2025", "equa": "ESP REUILLY 4", "equb": "ROSNY JA 1", "scorea": "16", "scoreb": "26", "compo_a": [{"nom": "JOURDREN Remi", "pts": 1762}, {"nom": "COEURET Guillaume", "pts": 1584}, {"nom": "BARJON Etienne", "pts": 1632}, {"nom": "FOVIAUX Luc", "pts": 1226}], "compo_b": [{"nom": "LOPEZ Victor", "pts": 1315}, {"nom": "MOUNAIX Olivier", "pts": 1516}, {"nom": "GUEDES Emmanuel", "pts": 1188}, {"nom": "SCHOTT Nicolas", "pts": 1228}]}, {"date": "29/11/2025", "equa": "ORMESSON US 1", "equb": "SAINT MAUR VGA US 3", "scorea": "18", "scoreb": "24", "compo_a": [{"nom": "DINCUFF Aimie", "pts": 880}, {"nom": "HOFFMANN-DRIF Tom", "pts": 1434}, {"nom": "CAPDELLAYRE Gary", "pts": 1724}, {"nom": "ARNOUT Frederic", "pts": 1247}], "compo_b": [{"nom": "YVONNET Nathan", "pts": 1342}, {"nom": "DELANNES Alexis", "pts": 1315}, {"nom": "DESVAQUET Hippolyte", "pts": 1335}, {"nom": "BOSC Alexis", "pts": 1646}]}, {"date": "29/11/2025", "equa": "NOISY LE GRAND 6", "equb": "ANTONY SPORT TT 3", "scorea": "20", "scoreb": "22", "compo_a": [{"nom": "TCHAKHOTINE Guillaume", "pts": 1637}, {"nom": "MONCANY Jeremy", "pts": 1448}, {"nom": "LISENA Mathis", "pts": 1434}, {"nom": "MEGUIRA Ruben", "pts": 1464}], "compo_b": [{"nom": "ROUSSEL Thibault", "pts": 1483}, {"nom": "MAYOMBO Tommy", "pts": 1624}, {"nom": "ZHANG Theo", "pts": 1465}, {"nom": "ION Alexandru", "pts": 1466}]}, {"date": "29/11/2025", "equa": "JUMP 5", "equb": "SQY PING 5", "scorea": "21", "scoreb": "20", "compo_a": [{"nom": "LEFEBURE Julien", "pts": 1239}, {"nom": "CHAN Mickael", "pts": 1437}, {"nom": "BOUDENNE Aurélien", "pts": 1438}, {"nom": "JOW Christophe", "pts": 1366}], "compo_b": [{"nom": "MERLINI Pascal", "pts": 1361}, {"nom": "SUAREZ Aurelien", "pts": 1318}, {"nom": "MONTMEAT Estelle", "pts": 1373}, {"nom": "WOLFF David", "pts": 1220}]}, {"date": "13/12/2025", "equa": "SAINT MAUR VGA US 3", "equb": "ESP REUILLY 4", "scorea": "24", "scoreb": "18", "compo_a": [{"nom": "YVONNET Nathan", "pts": 1342}, {"nom": "GRELLIER-COFFY Hugo", "pts": 1085}, {"nom": "BOUGEARD Matthieu", "pts": 1139}, {"nom": "GENIN Nicolas", "pts": 1457}], "compo_b": [{"nom": "LOPEZ Victor", "pts": 1315}, {"nom": "HUYNH BACH SAC Tom", "pts": 938}, {"nom": "CHEMOUL Jeremie", "pts": 1273}, {"nom": "SCHOTT Nicolas", "pts": 1228}]}, {"date": "13/12/2025", "equa": "ORMESSON US 1", "equb": "JUMP 5", "scorea": "22", "scoreb": "20", "compo_a": [{"nom": "HURE Sebastien", "pts": 1818}, {"nom": "DASSÉ Florian", "pts": 1324}, {"nom": "ROUSSEAU Romain", "pts": 1280}, {"nom": "HOFFMANN-DRIF Tom", "pts": 1434}], "compo_b": [{"nom": "BOUDENNE Aurélien", "pts": 1438}, {"nom": "CHAN Mickael", "pts": 1437}, {"nom": "JOW Christophe", "pts": 1366}, {"nom": "DAHERON Martin", "pts": 1371}]}, {"date": "13/12/2025", "equa": "ROSNY JA 1", "equb": "NOISY LE GRAND 6", "scorea": "26", "scoreb": "16", "compo_a": [{"nom": "COEURET Guillaume", "pts": 1584}, {"nom": "BARJON Etienne", "pts": 1632}, {"nom": "FOVIAUX Luc", "pts": 1226}, {"nom": "WILMUS Franck", "pts": 1371}], "compo_b": [{"nom": "LISENA Mathis", "pts": 1434}, {"nom": "MONCANY Jeremy", "pts": 1448}, {"nom": "DRAPIER Melanie", "pts": 1194}, {"nom": "RANDOUYER Patrice", "pts": 638}]}, {"date": "13/12/2025", "equa": "ANTONY SPORT TT 3", "equb": "SQY PING 5", "scorea": "24", "scoreb": "18", "compo_a": [{"nom": "MERLINI Pascal", "pts": 1361}, {"nom": "SUAREZ Aurelien", "pts": 1318}, {"nom": "WOLFF David", "pts": 1220}, {"nom": "BOUCHENDHOMME Alexandre", "pts": 1217}], "compo_b": [{"nom": "ZHANG Theo", "pts": 1465}, {"nom": "ION Alexandru", "pts": 1466}, {"nom": "MAYOMBO Tommy", "pts": 1624}, {"nom": "ROUSSEL Thibault", "pts": 1483}]}, {"date": "10/01/2026", "equa": "ESP REUILLY 4", "equb": "ORMESSON US 1", "scorea": "14", "scoreb": "28", "compo_a": [{"nom": "CHEMOUL David", "pts": 945}, {"nom": "SCHOTT Nicolas", "pts": 1228}, {"nom": "LOPEZ Victor", "pts": 1315}, {"nom": "ZAHRA Benoit", "pts": 731}], "compo_b": [{"nom": "CAPDELLAYRE Gary", "pts": 1724}, {"nom": "DASSÉ Florian", "pts": 1324}, {"nom": "HOFFMANN-DRIF Tom", "pts": 1434}, {"nom": "HURE Sebastien", "pts": 1818}]}, {"date": "10/01/2026", "equa": "NOISY LE GRAND 6", "equb": "SAINT MAUR VGA US 3", "scorea": "22", "scoreb": "20", "compo_a": [{"nom": "MEGUIRA Ruben", "pts": 1464}, {"nom": "MONCANY Jeremy", "pts": 1448}, {"nom": "ALTAF Ayaan", "pts": 1175}, {"nom": "LUIS Théo", "pts": 1418}], "compo_b": [{"nom": "YVONNET Nathan", "pts": 1342}, {"nom": "DESVAQUET Hippolyte", "pts": 1335}, {"nom": "GENIN Nicolas", "pts": 1457}, {"nom": "DELANNES Alexis", "pts": 1315}]}, {"date": "10/01/2026", "equa": "SQY PING 5", "equb": "ROSNY JA 1", "scorea": "19", "scoreb": "23", "compo_a": [{"nom": "SUAREZ Aurelien", "pts": 1318}, {"nom": "MERLINI Pascal", "pts": 1361}, {"nom": "MICHET HUET Gabriel", "pts": 1186}, {"nom": "BOUCHENDHOMME Alexandre", "pts": 1217}], "compo_b": [{"nom": "BARJON Etienne", "pts": 1632}, {"nom": "FOVIAUX Luc", "pts": 1226}, {"nom": "COEURET Guillaume", "pts": 1584}, {"nom": "WILMUS Franck", "pts": 1371}]}, {"date": "10/01/2026", "equa": "JUMP 5", "equb": "ANTONY SPORT TT 3", "scorea": "17", "scoreb": "25", "compo_a": [{"nom": "DAHERON Martin", "pts": 1371}, {"nom": "JOW Christophe", "pts": 1366}, {"nom": "BOUSQUET Vincent", "pts": 1293}, {"nom": "KEDIM Rayan", "pts": 1219}], "compo_b": [{"nom": "ROUSSEL Thibault", "pts": 1483}, {"nom": "ION Alexandru", "pts": 1466}, {"nom": "ZHANG Theo", "pts": 1465}, {"nom": "VIALLES Jean Michel", "pts": 1257}]}]}